Workbook

Sheet Read me
A1: Akelius Quiz Cards · History curriculum map
A2: Proposal from Jonas von Essen, 2026-10-15. Draft for discussion with Daniel Shea.
A4: What this file is
A5: A model curriculum for the history cards from level 1 to university, as asked for in the email "Quiz Card curricula" of 15 October 2026: key topics per tier, a rough number of cards per topic, outcomes for every level, and a mapping to an academic standard.
A6: Levels are school years 1 to 12 plus U for university. A card is labelled by subject and level, for example H 3. Tiers group the levels: 1-3, 4-6, 7-9 and 10-U.
A7: 400 cards already exist: 80 topics with five cards each, at levels 6, 9, 12, 12 and U. The map places all of them and proposes 1,119 new cards.
A9: Sheets
A10: Summary: cards per tier, level, phase, region, strand and era. The numbers are formulas and update when the other sheets change.
A11: Tiers: what each tier covers and what a card looks like there.
A12: Topics: the curriculum map. One row per topic and tier, with levels, content, card numbers, outcomes and standard mapping.
A13: Cards by level: the cards of each topic row split over the levels.
A14: Level outcomes: what students can do by the end of each level, with the standard each outcome maps to.
... A31: About 1,500 cards in all: the 400 that exist and 1,119 new. Tier 1-3: 223 new cards. Tier 4-6: 320 cards, of which 80 exist. Tier 7-9: 405 cards, of which 80 exist. Tier 10-U: 571 cards, of which 240 exist. Most levels get about 90 to 125 cards, two or three a week over a school year. Level 1 has fewer, since each card holds one fact and is read aloud, and level 4 covers only the first humans to the first metals. The Cards by level sheet gives the number for every row and level. We suggest two phases. Phase 1 has 553 new cards, about 950 with the existing ones, and covers every outcome at least once, every topic already on our list and the topics closest to pupils in Tanzania and Bhutan. Phase 2 adds the remaining 566 cards for depth.

Sheet Summary
A1: Cards per tier
A2: Tier | B2: Topic rows | C2: Existing cards | D2: New cards | E2: Total cards | F2: Share of total
A3: Tier 1-3 | B3: =COUNTIF(Topics!$B$2:$B$213,A3) -> 31 | C3: =SUMIF(Topics!$B$2:$B$213,A3,Topics!$K$2:$K$213) -> 0 | D3: =SUMIF(Topics!$B$2:$B$213,A3,Topics!$L$2:$L$213) -> 223 | E3: =C3+D3 -> 223 | F3: =IF($E$7=0,0,E3/$E$7) -> 0.14680711
A4: Tier 4-6 | B4: =COUNTIF(Topics!$B$2:$B$213,A4) -> 46 | C4: =SUMIF(Topics!$B$2:$B$213,A4,Topics!$K$2:$K$213) -> 80 | D4: =SUMIF(Topics!$B$2:$B$213,A4,Topics!$L$2:$L$213) -> 240 | E4: =C4+D4 -> 320 | F4: =IF($E$7=0,0,E4/$E$7) -> 0.21066491
A5: Tier 7-9 | B5: =COUNTIF(Topics!$B$2:$B$213,A5) -> 72 | C5: =SUMIF(Topics!$B$2:$B$213,A5,Topics!$K$2:$K$213) -> 80 | D5: =SUMIF(Topics!$B$2:$B$213,A5,Topics!$L$2:$L$213) -> 325 | E5: =C5+D5 -> 405 | F5: =IF($E$7=0,0,E5/$E$7) -> 0.26662278
A6: Tier 10-U | B6: =COUNTIF(Topics!$B$2:$B$213,A6) -> 63 | C6: =SUMIF(Topics!$B$2:$B$213,A6,Topics!$K$2:$K$213) -> 240 | D6: =SUMIF(Topics!$B$2:$B$213,A6,Topics!$L$2:$L$213) -> 331 | E6: =C6+D6 -> 571 | F6: =IF($E$7=0,0,E6/$E$7) -> 0.3759052
A7: All tiers | B7: =SUM(B3:B6) -> 212 | C7: =SUM(C3:C6) -> 400 | D7: =SUM(D3:D6) -> 1119 | E7: =SUM(E3:E6) -> 1519 | F7: =IF($E$7=0,0,E7/$E$7) -> 1
A9: Cards per level
A10: Level | B10: Existing cards | C10: New cards | D10: Total cards
A11: Level 1 | B11: =COUNTIF('Existing cards'!$D$2:$D$401,"H 1") -> 0 | C11: =D11-B11 -> 51 | D11: =SUM('Cards by level'!D2:D213) -> 51
A12: Level 2 | B12: =COUNTIF('Existing cards'!$D$2:$D$401,"H 2") -> 0 | C12: =D12-B12 -> 68 | D12: =SUM('Cards by level'!E2:E213) -> 68
A13: Level 3 | B13: =COUNTIF('Existing cards'!$D$2:$D$401,"H 3") -> 0 | C13: =D13-B13 -> 104 | D13: =SUM('Cards by level'!F2:F213) -> 104
A14: Level 4 | B14: =COUNTIF('Existing cards'!$D$2:$D$401,"H 4") -> 0 | C14: =D14-B14 -> 62 | D14: =SUM('Cards by level'!G2:G213) -> 62
A15: Level 5 | B15: =COUNTIF('Existing cards'!$D$2:$D$401,"H 5") -> 0 | C15: =D15-B15 -> 87 | D15: =SUM('Cards by level'!H2:H213) -> 87
A16: Level 6 | B16: =COUNTIF('Existing cards'!$D$2:$D$401,"H 6") -> 80 | C16: =D16-B16 -> 91 | D16: =SUM('Cards by level'!I2:I213) -> 171
A17: Level 7 | B17: =COUNTIF('Existing cards'!$D$2:$D$401,"H 7") -> 0 | C17: =D17-B17 -> 120 | D17: =SUM('Cards by level'!J2:J213) -> 120
A18: Level 8 | B18: =COUNTIF('Existing cards'!$D$2:$D$401,"H 8") -> 0 | C18: =D18-B18 -> 100 | D18: =SUM('Cards by level'!K2:K213) -> 100
A19: Level 9 | B19: =COUNTIF('Existing cards'!$D$2:$D$401,"H 9") -> 80 | C19: =D19-B19 -> 105 | D19: =SUM('Cards by level'!L2:L213) -> 185
A20: Level 10 | B20: =COUNTIF('Existing cards'!$D$2:$D$401,"H 10") -> 0 | C20: =D20-B20 -> 89 | D20: =SUM('Cards by level'!M2:M213) -> 89
A21: Level 11 | B21: =COUNTIF('Existing cards'!$D$2:$D$401,"H 11") -> 0 | C21: =D21-B21 -> 125 | D21: =SUM('Cards by level'!N2:N213) -> 125
A22: Level 12 | B22: =COUNTIF('Existing cards'!$D$2:$D$401,"H 12") -> 160 | C22: =D22-B22 -> 78 | D22: =SUM('Cards by level'!O2:O213) -> 238
A23: Level U | B23: =COUNTIF('Existing cards'!$D$2:$D$401,"H U") -> 80 | C23: =D23-B23 -> 39 | D23: =SUM('Cards by level'!P2:P213) -> 119
A24: All levels | B24: =SUM(B11:B23) -> 400 | C24: =SUM(C11:C23) -> 1119 | D24: =SUM(D11:D23) -> 1519
A26: Cards per phase
A27: Value | B27: Topic rows | C27: Existing cards | D27: New cards | E27: Total cards | F27: Share of total
A28: Phase 1 | B28: =COUNTIF(Topics!$J$2:$J$213,A28) -> 83 | C28: =SUMIF(Topics!$J$2:$J$213,A28,Topics!$K$2:$K$213) -> 31 | D28: =SUMIF(Topics!$J$2:$J$213,A28,Topics!$L$2:$L$213) -> 553 | E28: =C28+D28 -> 584 | F28: =IF($E$7=0,0,E28/$E$7) -> 0.38446346
A29: Phase 2 | B29: =COUNTIF(Topics!$J$2:$J$213,A29) -> 110 | C29: =SUMIF(Topics!$J$2:$J$213,A29,Topics!$K$2:$K$213) -> 241 | D29: =SUMIF(Topics!$J$2:$J$213,A29,Topics!$L$2:$L$213) -> 566 | E29: =C29+D29 -> 807 | F29: =IF($E$7=0,0,E29/$E$7) -> 0.53127057
A30: Existing only | B30: =COUNTIF(Topics!$J$2:$J$213,A30) -> 19 | C30: =SUMIF(Topics!$J$2:$J$213,A30,Topics!$K$2:$K$213) -> 128 | D30: =SUMIF(Topics!$J$2:$J$213,A30,Topics!$L$2:$L$213) -> 0 | E30: =C30+D30 -> 128 | F30: =IF($E$7=0,0,E30/$E$7) -> 0.084265964
A32: Cards per region
A33: Value | B33: Topic rows | C33: Existing cards | D33: New cards | E33: Total cards | F33: Share of total
A34: Africa | B34: =COUNTIF(Topics!$G$2:$G$213,A34) -> 35 | C34: =SUMIF(Topics!$G$2:$G$213,A34,Topics!$K$2:$K$213) -> 24 | D34: =SUMIF(Topics!$G$2:$G$213,A34,Topics!$L$2:$L$213) -> 226 | E34: =C34+D34 -> 250 | F34: =IF($E$7=0,0,E34/$E$7) -> 0.16458196
A35: Asia and Pacific | B35: =COUNTIF(Topics!$G$2:$G$213,A35) -> 41 | C35: =SUMIF(Topics!$G$2:$G$213,A35,Topics!$K$2:$K$213) -> 33 | D35: =SUMIF(Topics!$G$2:$G$213,A35,Topics!$L$2:$L$213) -> 209 | E35: =C35+D35 -> 242 | F35: =IF($E$7=0,0,E35/$E$7) -> 0.15931534
A36: Europe | B36: =COUNTIF(Topics!$G$2:$G$213,A36) -> 35 | C36: =SUMIF(Topics!$G$2:$G$213,A36,Topics!$K$2:$K$213) -> 115 | D36: =SUMIF(Topics!$G$2:$G$213,A36,Topics!$L$2:$L$213) -> 132 | E36: =C36+D36 -> 247 | F36: =IF($E$7=0,0,E36/$E$7) -> 0.16260698
A37: Global | B37: =COUNTIF(Topics!$G$2:$G$213,A37) -> 69 | C37: =SUMIF(Topics!$G$2:$G$213,A37,Topics!$K$2:$K$213) -> 174 | D37: =SUMIF(Topics!$G$2:$G$213,A37,Topics!$L$2:$L$213) -> 402 | E37: =C37+D37 -> 576 | F37: =IF($E$7=0,0,E37/$E$7) -> 0.37919684
A38: Latin America | B38: =COUNTIF(Topics!$G$2:$G$213,A38) -> 13 | C38: =SUMIF(Topics!$G$2:$G$213,A38,Topics!$K$2:$K$213) -> 15 | D38: =SUMIF(Topics!$G$2:$G$213,A38,Topics!$L$2:$L$213) -> 63 | E38: =C38+D38 -> 78 | F38: =IF($E$7=0,0,E38/$E$7) -> 0.051349572
A39: Middle East | B39: =COUNTIF(Topics!$G$2:$G$213,A39) -> 13 | C39: =SUMIF(Topics!$G$2:$G$213,A39,Topics!$K$2:$K$213) -> 34 | D39: =SUMIF(Topics!$G$2:$G$213,A39,Topics!$L$2:$L$213) -> 64 | E39: =C39+D39 -> 98 | F39: =IF($E$7=0,0,E39/$E$7) -> 0.064516129
A40: North America | B40: =COUNTIF(Topics!$G$2:$G$213,A40) -> 6 | C40: =SUMIF(Topics!$G$2:$G$213,A40,Topics!$K$2:$K$213) -> 5 | D40: =SUMIF(Topics!$G$2:$G$213,A40,Topics!$L$2:$L$213) -> 23 | E40: =C40+D40 -> 28 | F40: =IF($E$7=0,0,E40/$E$7) -> 0.01843318
A42: Cards per strand
A43: Value | B43: Topic rows | C43: Existing cards | D43: New cards | E43: Total cards | F43: Share of total
A44: belief and ideas | B44: =COUNTIF(Topics!$H$2:$H$213,A44) -> 26 | C44: =SUMIF(Topics!$H$2:$H$213,A44,Topics!$K$2:$K$213) -> 97 | D44: =SUMIF(Topics!$H$2:$H$213,A44,Topics!$L$2:$L$213) -> 121 | E44: =C44+D44 -> 218 | F44: =IF($E$7=0,0,E44/$E$7) -> 0.14351547
A45: conflict and peace | B45: =COUNTIF(Topics!$H$2:$H$213,A45) -> 8 | C45: =SUMIF(Topics!$H$2:$H$213,A45,Topics!$K$2:$K$213) -> 19 | D45: =SUMIF(Topics!$H$2:$H$213,A45,Topics!$L$2:$L$213) -> 42 | E45: =C45+D45 -> 61 | F45: =IF($E$7=0,0,E45/$E$7) -> 0.040157999
A46: empire and colonialism | B46: =COUNTIF(Topics!$H$2:$H$213,A46) -> 10 | C46: =SUMIF(Topics!$H$2:$H$213,A46,Topics!$K$2:$K$213) -> 4 | D46: =SUMIF(Topics!$H$2:$H$213,A46,Topics!$L$2:$L$213) -> 64 | E46: =C46+D46 -> 68 | F46: =IF($E$7=0,0,E46/$E$7) -> 0.044766294
A47: environment | B47: =COUNTIF(Topics!$H$2:$H$213,A47) -> 3 | C47: =SUMIF(Topics!$H$2:$H$213,A47,Topics!$K$2:$K$213) -> 0 | D47: =SUMIF(Topics!$H$2:$H$213,A47,Topics!$L$2:$L$213) -> 17 | E47: =C47+D47 -> 17 | F47: =IF($E$7=0,0,E47/$E$7) -> 0.011191573
A48: people and everyday life | B48: =COUNTIF(Topics!$H$2:$H$213,A48) -> 32 | C48: =SUMIF(Topics!$H$2:$H$213,A48,Topics!$K$2:$K$213) -> 15 | D48: =SUMIF(Topics!$H$2:$H$213,A48,Topics!$L$2:$L$213) -> 205 | E48: =C48+D48 -> 220 | F48: =IF($E$7=0,0,E48/$E$7) -> 0.14483213
A49: power and government | B49: =COUNTIF(Topics!$H$2:$H$213,A49) -> 47 | C49: =SUMIF(Topics!$H$2:$H$213,A49,Topics!$K$2:$K$213) -> 45 | D49: =SUMIF(Topics!$H$2:$H$213,A49,Topics!$L$2:$L$213) -> 242 | E49: =C49+D49 -> 287 | F49: =IF($E$7=0,0,E49/$E$7) -> 0.18894009
A50: rights, freedom and equality | B50: =COUNTIF(Topics!$H$2:$H$213,A50) -> 14 | C50: =SUMIF(Topics!$H$2:$H$213,A50,Topics!$K$2:$K$213) -> 36 | D50: =SUMIF(Topics!$H$2:$H$213,A50,Topics!$L$2:$L$213) -> 64 | E50: =C50+D50 -> 100 | F50: =IF($E$7=0,0,E50/$E$7) -> 0.065832785
A51: science, technology and mathematics | B51: =COUNTIF(Topics!$H$2:$H$213,A51) -> 24 | C51: =SUMIF(Topics!$H$2:$H$213,A51,Topics!$K$2:$K$213) -> 32 | D51: =SUMIF(Topics!$H$2:$H$213,A51,Topics!$L$2:$L$213) -> 152 | E51: =C51+D51 -> 184 | F51: =IF($E$7=0,0,E51/$E$7) -> 0.12113232
A52: time and evidence | B52: =COUNTIF(Topics!$H$2:$H$213,A52) -> 22 | C52: =SUMIF(Topics!$H$2:$H$213,A52,Topics!$K$2:$K$213) -> 124 | D52: =SUMIF(Topics!$H$2:$H$213,A52,Topics!$L$2:$L$213) -> 84 | E52: =C52+D52 -> 208 | F52: =IF($E$7=0,0,E52/$E$7) -> 0.13693219
A53: trade, travel and exchange | B53: =COUNTIF(Topics!$H$2:$H$213,A53) -> 26 | C53: =SUMIF(Topics!$H$2:$H$213,A53,Topics!$K$2:$K$213) -> 28 | D53: =SUMIF(Topics!$H$2:$H$213,A53,Topics!$L$2:$L$213) -> 128 | E53: =C53+D53 -> 156 | F53: =IF($E$7=0,0,E53/$E$7) -> 0.10269914
A55: Cards per era
A56: Value | B56: Topic rows | C56: Existing cards | D56: New cards | E56: Total cards | F56: Share of total
A57: Across time | B57: =COUNTIF(Topics!$F$2:$F$213,A57) -> 19 | C57: =SUMIF(Topics!$F$2:$F$213,A57,Topics!$K$2:$K$213) -> 0 | D57: =SUMIF(Topics!$F$2:$F$213,A57,Topics!$L$2:$L$213) -> 137 | E57: =C57+D57 -> 137 | F57: =IF($E$7=0,0,E57/$E$7) -> 0.090190915
A58: Big Era 1, before 200,000 years ago | B58: =COUNTIF(Topics!$F$2:$F$213,A58) -> 3 | C58: =SUMIF(Topics!$F$2:$F$213,A58,Topics!$K$2:$K$213) -> 0 | D58: =SUMIF(Topics!$F$2:$F$213,A58,Topics!$L$2:$L$213) -> 24 | E58: =C58+D58 -> 24 | F58: =IF($E$7=0,0,E58/$E$7) -> 0.015799868
A59: Big Era 2, 200,000 to 10,000 years ago | B59: =COUNTIF(Topics!$F$2:$F$213,A59) -> 5 | C59: =SUMIF(Topics!$F$2:$F$213,A59,Topics!$K$2:$K$213) -> 0 | D59: =SUMIF(Topics!$F$2:$F$213,A59,Topics!$L$2:$L$213) -> 34 | E59: =C59+D59 -> 34 | F59: =IF($E$7=0,0,E59/$E$7) -> 0.022383147
A60: Big Era 3, 8000-1000 BCE | B60: =COUNTIF(Topics!$F$2:$F$213,A60) -> 13 | C60: =SUMIF(Topics!$F$2:$F$213,A60,Topics!$K$2:$K$213) -> 19 | D60: =SUMIF(Topics!$F$2:$F$213,A60,Topics!$L$2:$L$213) -> 80 | E60: =C60+D60 -> 99 | F60: =IF($E$7=0,0,E60/$E$7) -> 0.065174457
A61: Big Era 4, 1200 BCE to 500 CE | B61: =COUNTIF(Topics!$F$2:$F$213,A61) -> 20 | C61: =SUMIF(Topics!$F$2:$F$213,A61,Topics!$K$2:$K$213) -> 65 | D61: =SUMIF(Topics!$F$2:$F$213,A61,Topics!$L$2:$L$213) -> 75 | E61: =C61+D61 -> 140 | F61: =IF($E$7=0,0,E61/$E$7) -> 0.092165899
A62: Big Era 5, 300-1500 CE | B62: =COUNTIF(Topics!$F$2:$F$213,A62) -> 28 | C62: =SUMIF(Topics!$F$2:$F$213,A62,Topics!$K$2:$K$213) -> 74 | D62: =SUMIF(Topics!$F$2:$F$213,A62,Topics!$L$2:$L$213) -> 125 | E62: =C62+D62 -> 199 | F62: =IF($E$7=0,0,E62/$E$7) -> 0.13100724
A63: Big Era 6, 1400-1800 | B63: =COUNTIF(Topics!$F$2:$F$213,A63) -> 21 | C63: =SUMIF(Topics!$F$2:$F$213,A63,Topics!$K$2:$K$213) -> 63 | D63: =SUMIF(Topics!$F$2:$F$213,A63,Topics!$L$2:$L$213) -> 96 | E63: =C63+D63 -> 159 | F63: =IF($E$7=0,0,E63/$E$7) -> 0.10467413
A64: Big Era 7, 1750-1914 | B64: =COUNTIF(Topics!$F$2:$F$213,A64) -> 26 | C64: =SUMIF(Topics!$F$2:$F$213,A64,Topics!$K$2:$K$213) -> 47 | D64: =SUMIF(Topics!$F$2:$F$213,A64,Topics!$L$2:$L$213) -> 122 | E64: =C64+D64 -> 169 | F64: =IF($E$7=0,0,E64/$E$7) -> 0.11125741
A65: Big Era 8, 1900-1950 | B65: =COUNTIF(Topics!$F$2:$F$213,A65) -> 12 | C65: =SUMIF(Topics!$F$2:$F$213,A65,Topics!$K$2:$K$213) -> 23 | D65: =SUMIF(Topics!$F$2:$F$213,A65,Topics!$L$2:$L$213) -> 66 | E65: =C65+D65 -> 89 | F65: =IF($E$7=0,0,E65/$E$7) -> 0.058591178
A66: Big Era 9, 1945 to today | B66: =COUNTIF(Topics!$F$2:$F$213,A66) -> 23 | C66: =SUMIF(Topics!$F$2:$F$213,A66,Topics!$K$2:$K$213) -> 32 | D66: =SUMIF(Topics!$F$2:$F$213,A66,Topics!$L$2:$L$213) -> 124 | E66: =C66+D66 -> 156 | F66: =IF($E$7=0,0,E66/$E$7) -> 0.10269914
A67: Big Eras 2-4, 200,000 years ago to 500 CE | B67: =COUNTIF(Topics!$F$2:$F$213,A67) -> 1 | C67: =SUMIF(Topics!$F$2:$F$213,A67,Topics!$K$2:$K$213) -> 0 | D67: =SUMIF(Topics!$F$2:$F$213,A67,Topics!$L$2:$L$213) -> 5 | E67: =C67+D67 -> 5 | F67: =IF($E$7=0,0,E67/$E$7) -> 0.0032916392
A68: Big Eras 3-4, 8000 BCE to 500 CE | B68: =COUNTIF(Topics!$F$2:$F$213,A68) -> 5 | C68: =SUMIF(Topics!$F$2:$F$213,A68,Topics!$K$2:$K$213) -> 1 | D68: =SUMIF(Topics!$F$2:$F$213,A68,Topics!$L$2:$L$213) -> 27 | E68: =C68+D68 -> 28 | F68: =IF($E$7=0,0,E68/$E$7) -> 0.01843318
... A80: Big Eras 8-9, 1900 to today | B80: =COUNTIF(Topics!$F$2:$F$213,A80) -> 4 | C80: =SUMIF(Topics!$F$2:$F$213,A80,Topics!$K$2:$K$213) -> 25 | D80: =SUMIF(Topics!$F$2:$F$213,A80,Topics!$L$2:$L$213) -> 31 | E80: =C80+D80 -> 56 | F80: =IF($E$7=0,0,E80/$E$7) -> 0.036866359
A82: Outcomes per level
A83: Level | B83: Outcomes
A84: Level 1 | B84: =COUNTIF('Level outcomes'!$A$2:$A$104,"1") -> 7
A85: Level 2 | B85: =COUNTIF('Level outcomes'!$A$2:$A$104,"2") -> 8
A86: Level 3 | B86: =COUNTIF('Level outcomes'!$A$2:$A$104,"3") -> 8
A87: Level 4 | B87: =COUNTIF('Level outcomes'!$A$2:$A$104,"4") -> 8
A88: Level 5 | B88: =COUNTIF('Level outcomes'!$A$2:$A$104,"5") -> 8
A89: Level 6 | B89: =COUNTIF('Level outcomes'!$A$2:$A$104,"6") -> 8
A90: Level 7 | B90: =COUNTIF('Level outcomes'!$A$2:$A$104,"7") -> 8
A91: Level 8 | B91: =COUNTIF('Level outcomes'!$A$2:$A$104,"8") -> 8
A92: Level 9 | B92: =COUNTIF('Level outcomes'!$A$2:$A$104,"9") -> 8
A93: Level 10 | B93: =COUNTIF('Level outcomes'!$A$2:$A$104,"10") -> 8
A94: Level 11 | B94: =COUNTIF('Level outcomes'!$A$2:$A$104,"11") -> 8
A95: Level 12 | B95: =COUNTIF('Level outcomes'!$A$2:$A$104,"12") -> 8
A96: Level U | B96: =COUNTIF('Level outcomes'!$A$2:$A$104,"U") -> 8

Sheet Topics
A1: Topic ID | B1: Tier | C1: Levels | D1: Topic | E1: Key content | F1: Era | G1: Region | H1: Strand | I1: Status | J1: Phase | K1: Existing cards | L1: New cards | M1: Total cards | N1: Outcomes | O1: Standard mapping | P1: Existing card set | Q1: Notes
A2: T1-3-001 | B2: Tier 1-3 | C2: 1 | D2: Time words, days and calendars | E2: Before and after, moon months, the farming year, counting days by sun, moon and rain. | F2: Across time | G2: Global | H2: time and evidence | I2: new | J2: Phase 1 | K2: 0 | L2: 10 | M2: =K2+L2 -> 10 | N2: H1.1 | O2: NCHS K-4 Historical Thinking Standard 1, Chronological Thinking; BNCC EF02HI06; Cambridge Primary Humanities 0065, Past strand | Q2: By level: 1: 10 new. Phase 1.
A3: T1-3-002 | B3: Tier 1-3 | C3: 1, 2 | D3: Children, families and school then and now | E3: Chores, games and toys, a grandparent's childhood, learning from elders, scribe and monastery schools. | F3: Across time | G3: Global | H3: people and everyday life | I3: new | J3: Phase 2 | K3: 0 | L3: 12 | M3: =K3+L3 -> 12 | N3: H1.3, H2.7 | O3: NCHS K-4 Topic 1, Standard 1; Tanzania HTM primary 2023, Std III | Q3: By level: 1: 7 new; 2: 5 new. Childhood is a gap in the existing sets. Many pupils still learn at home and in monastery schools, so cards show what changed and what stayed. Phase 2.
A4: T1-3-003 | B4: Tier 1-3 | C4: 1, 2 | D4: Homes, tools and food through time | E4: Round huts and stilt houses, cooking fire to stove, oil lamp to bulb, clay pot to metal pot. | F4: Across time | G4: Global | H4: people and everyday life | I4: new | J4: Phase 2 | K4: 0 | L4: 10 | M4: =K4+L4 -> 10 | N4: H1.2, H1.3, H2.7 | O4: NCHS K-4 Topic 4, Standard 8A; NCHS K-4 Topic 1, Standard 1 | Q4: By level: 1: 6 new; 2: 4 new. The Himalayan farmhouse and grinding grain belong to T1-3-030. Phase 2.
A5: T1-3-004 | B5: Tier 1-3 | C5: 1, 2 | D5: Clues from the past | E5: Objects, photos, buildings, bones and stories; what museums and archaeologists do. | F5: Across time | G5: Global | H5: time and evidence | I5: new | J5: Phase 1 | K5: 0 | L5: 10 | M5: =K5+L5 -> 10 | N5: H1.4, H2.6 | O5: Cambridge Primary Humanities 0065, Past strand, how we construct the past; NCHS K-4 Topic 4, Standard 7A | Q5: By level: 1: 6 new; 2: 4 new. Phase 1.
A6: T1-3-005 | B6: Tier 1-3 | C6: 1, 2 | D6: Stories, songs and festivals | E6: Harvest and new year festivals, masked dances in Bhutan, Anansi and the clever hare. | F6: Across time | G6: Global | H6: belief and ideas | I6: new | J6: Phase 2 | K6: 0 | L6: 10 | M6: =K6+L6 -> 10 | N6: H1.5, H2.8 | O6: NCHS K-4 Topic 4, Standard 7A, folktales, holidays and ceremonies; Tanzania HTM primary 2023, Std III | Q6: By level: 1: 6 new; 2: 4 new. Faith festivals are shown as what believers do. Phase 2.
A7: T1-3-006 | B7: Tier 1-3 | C7: 1, 2, 3 | D7: Travel and messages, from feet to rockets | E7: Camels, canoes, trains and planes; runners, talking drums, letters and satellites. | F7: Across time | G7: Global | H7: trade, travel and exchange | I7: new | J7: Phase 1 | K7: 0 | L7: 10 | M7: =K7+L7 -> 10 | N7: H1.6, H2.8, H3.4 | O7: NCHS K-4 Topic 4, Standards 8B and 8C | Q7: By level: 1: 5 new; 2: 3 new; 3: 2 new. Phase 1.
A8: T1-3-007 | B8: Tier 1-3 | C8: 1 | D8: Leaders and rules: elders, chiefs and councils | E8: Who makes rules at home, at school and in a village; clan elders and chiefs in East Africa long ago; choosing leaders today. | F8: Across time | G8: Africa | H8: power and government | I8: new | J8: Phase 1 | K8: 0 | L8: 6 | M8: =K8+L8 -> 6 | N8: H1.7 | O8: WHFUA key theme Uses and Abuses of Power; Tanzania HTM primary 2023, Std III; Bhutan Social Studies 2025, Class IV | Q8: By level: 1: 6 new. Neutral tone, not the HTM values framing. Named systems such as Maasai age sets and Buganda belong to T4-6-038. Phase 1.
A9: T1-3-008 | B9: Tier 1-3 | C9: 2 | D9: Our oldest ancestors, in East Africa | E9: Laetoli footprints and Lucy as human ancestors, not people like us; Olduvai tools; how we know people began in Africa. | F9: Big Era 1, before 200,000 years ago | G9: Africa | H9: people and everyday life | I9: new | J9: Phase 1 | K9: 0 | L9: 8 | M9: =K9+L9 -> 8 | N9: H2.1, H2.6 | O9: WHFUA Big Era 1, Landscape 1.2; NCHS World History Era 1, Standard 1 | Q9: By level: 2: 8 new. The most local topic for Tanzania. Cards say 'the oldest found so far'. Laetoli, Olduvai and Lucy belong to this row. Phase 1.
A10: T1-3-009 | B10: Tier 1-3 | C10: 2 | D10: Stone tools, fire and shelter | E10: Hand axes, blades, cooking with fire, clothes and shelters. | F10: Big Era 2, 200,000 to 10,000 years ago | G10: Global | H10: science, technology and mathematics | I10: new | J10: Phase 1 | K10: 0 | L10: 7 | M10: =K10+L10 -> 7 | N10: H2.3 | O10: NCHS K-4 Topic 4, Standard 8A | Q10: By level: 2: 7 new. Say people used fire for a very long time; no exact first dates at this level. Phase 1.
A11: T1-3-010 | B11: Tier 1-3 | C11: 2 | D11: Hunting, fishing and gathering | E11: Finding fruit, roots, fish and meat, moving with the seasons. | F11: Big Era 2, 200,000 to 10,000 years ago | G11: Global | H11: people and everyday life | I11: new | J11: Phase 1 | K11: 0 | L11: 6 | M11: =K11+L11 -> 6 | N11: H2.2 | O11: NCHS K-4 Topic 4, Standard 8A; WHFUA Big Era 2, Landscape 2.1 | Q11: By level: 2: 6 new. Living hunter-gatherers, such as the Hadza of Tanzania, are shown with respect and in the present. Phase 1.
A12: T1-3-011 | B12: Tier 1-3 | C12: 2 | D12: Rock art and beads | E12: Hand stencils on Sulawesi, ostrich-egg beads, Australian rock art. | F12: Big Era 2, 200,000 to 10,000 years ago | G12: Global | H12: belief and ideas | I12: new | J12: Phase 1 | K12: 0 | L12: 6 | M12: =K12+L12 -> 6 | N12: H2.4 | O12: WHFUA Big Era 2, Landscape 2.1; NCHS K-4 Topic 4, Standard 7A | Q12: By level: 2: 6 new. Blombos and Lascaux belong to T4-6-005 and the Kondoa paintings to T1-3-029. Phase 1.
A13: T1-3-012 | B13: Tier 1-3 | C13: 2 | D13: People reach every continent | E13: Walking out of Africa, the first boats across the sea, crossing the land bridge to the Americas. | F13: Big Era 2, 200,000 to 10,000 years ago | G13: Global | H13: trade, travel and exchange | I13: new | J13: Phase 1 | K13: 0 | L13: 6 | M13: =K13+L13 -> 6 | N13: H2.5 | O13: NCHS K-4 Topic 4, Standard 7B; WHFUA Big Era 2, Landscape 2.1 | Q13: By level: 2: 6 new. Phase 1.
... A40: T4-6-008 | B40: Tier 4-6 | C40: 4 | D40: Metals, wheels and horses | E40: Copper and bronze, wheels, the tamed horse, chariots, iron. | F40: Big Era 3, 8000-1000 BCE | G40: Global | H40: science, technology and mathematics | I40: new | J40: Phase 1 | K40: 0 | L40: 8 | M40: =K40+L40 -> 8 | N40: H4.7 | O40: NCHS World History Era 2, Standard 3; WHFUA Big Era 3, Landscape 3.4 | Q40: By level: 4: 8 new. Phase 1.
A41: T4-6-009 | B41: Tier 4-6 | C41: 5, 6 | D41: Ancient Egypt | E41: Hatshepsut and the voyage to Punt, the Deir el-Medina tomb builders and the first recorded strike, Akhenaten's one-god belief marked as belief, medicine on papyrus. | F41: Big Era 3, 8000-1000 BCE | G41: Africa | H41: people and everyday life | I41: existing + new | J41: Phase 2 | K41: 1 | L41: 6 | M41: =K41+L41 -> 7 | N41: H5.1, H5.3, H5.6, H6.7 | O41: NCHS World History Era 2, Standard 1; WHFUA Big Era 3, Landscape 3.3; Kenya KICD Junior School Grade 7 | P41: ancient-egypt-pyramids | Q41: By level: 5: 4 new; 6: 2 new, 1 existing. Counted as Africa. The Nile farmers, scribes, hieroglyphs, the afterlife and the Rosetta Stone are on the existing cards. Phase 2.
A42: T4-6-010 | B42: Tier 4-6 | C42: 5, 6 | D42: Mesopotamia and the first law codes | E42: Sargon of Akkad, Enheduanna the first named author, counting in sixties, the library of Nineveh. | F42: Big Era 3, 8000-1000 BCE | G42: Middle East | H42: power and government | I42: existing + new | J42: Phase 2 | K42: 2 | L42: 5 | M42: =K42+L42 -> 7 | N42: H5.1, H5.2, H5.5, H6.7 | O42: NCHS World History Era 2, Standard 1; WHFUA Big Era 3, Landscape 3.3; England National Curriculum 2013, KS2, Sumer | P42: mesopotamia, hammurabi | Q42: By level: 5: 5 new; 6: 2 existing. Ziggurats, cuneiform, Babylon and the law stone are on the existing cards. Phase 2.
A43: T4-6-011 | B43: Tier 4-6 | C43: 5 | D43: The Indus valley civilisation | E43: Harappa, Mohenjo-daro, drains, weights, seals, an unread script, why the cities declined. | F43: Big Era 3, 8000-1000 BCE | G43: Asia and Pacific | H43: people and everyday life | I43: new | J43: Phase 2 | K43: 0 | L43: 8 | M43: =K43+L43 -> 8 | N43: H5.1, H5.5, H5.7 | O43: NCHS World History Era 2, Standard 1; WHFUA Big Era 3, Landscape 3.3; NCERT Exploring Society Grade 6 | Q43: By level: 5: 8 new. A gap in the existing sets. Cities declined as rivers and rain changed; there was no Aryan invasion. Seals are shown without readable signs. Phase 2.
A44: T4-6-012 | B44: Tier 4-6 | C44: 5 | D44: Early China: Shang and Zhou | E44: Oracle bones, bronze casting, the Mandate of Heaven. | F44: Big Era 3, 8000-1000 BCE | G44: Asia and Pacific | H44: power and government | I44: new | J44: Phase 2 | K44: 0 | L44: 6 | M44: =K44+L44 -> 6 | N44: H5.1, H5.2 | O44: NCHS World History Era 2, Standard 2; WHFUA Big Era 3, Landscape 3.3; England National Curriculum 2013, KS2, Shang | Q44: By level: 5: 6 new. A gap in the existing sets. Oracle bones are shown without readable characters. Phase 2.
A45: T4-6-013 | B45: Tier 4-6 | C45: 5 | D45: How writing began around the world | E45: Writing invented separately in Mesoamerica; Linear B read by Michael Ventris. | F45: Big Eras 3-4, 8000 BCE to 500 CE | G45: Global | H45: science, technology and mathematics | I45: new | J45: Phase 1 | K45: 0 | L45: 2 | M45: =K45+L45 -> 2 | N45: H5.2, H5.7 | O45: NCHS World History Era 2, 1A; WHFUA Big Era 4, Landscape 4.6 | Q45: By level: 5: 2 new. Writing in Mesopotamia and old scripts read again are on existing cards. Avoid the Rosetta Stone motif. No readable signs in images. Phase 1.
A46: T4-6-014 | B46: Tier 4-6 | C46: 5, 6 | D46: Kush and Nubia | E46: Kerma, the pharaohs from the south, iron and pyramids of Meroe. | F46: Big Eras 3-4, 8000 BCE to 500 CE | G46: Africa | H46: power and government | I46: planned | J46: Phase 1 | K46: 0 | L46: 7 | M46: =K46+L46 -> 7 | N46: H5.4, H6.1 | O46: NCHS World History Era 3, 1C; WHFUA Big Era 4, Landscape 4.3; Kenya KICD Junior School Grade 8 | Q46: By level: 5: 5 new; 6: 2 new. Raised from 3 to 7 cards because Egypt is the only ancient African state in the existing sets. Planned topic #89 on the Akelius topic list. Phase 1.
A47: T4-6-015 | B47: Tier 4-6 | C47: 5 | D47: Bronze Age Crete, Mycenae and the collapse | E47: Minoan palaces, the tin trade, the fall of states around 1200 BCE. | F47: Big Era 3, 8000-1000 BCE | G47: Europe | H47: trade, travel and exchange | I47: new | J47: Phase 2 | K47: 0 | L47: 4 | M47: =K47+L47 -> 4 | N47: H5.4 | O47: NCHS World History Era 2, 2B and Standard 3 | Q47: By level: 5: 4 new. Phase 2.
A48: T4-6-016 | B48: Tier 4-6 | C48: 5 | D48: First civilisations of the Americas | E48: Caral, the Olmec, Chavin, Teotihuacan, Moche, Nazca. | F48: Big Eras 3-4, 8000 BCE to 500 CE | G48: Latin America | H48: people and everyday life | I48: new | J48: Phase 1 | K48: 0 | L48: 8 | M48: =K48+L48 -> 8 | N48: H5.4 | O48: NCHS World History Era 3, Standard 4; WHFUA Big Era 3, Landscape 3.5, and Big Era 4, Landscape 4.6 | Q48: By level: 5: 8 new. A gap in the existing sets, which start the Americas with the Maya. Phase 1.
A49: T4-6-017 | B49: Tier 4-6 | C49: 5, 6 | D49: The Phoenicians, Carthage and the voyage of Hanno | E49: Hanno's voyage along West Africa, Carthage's harbour and farms, Hannibal. | F49: Big Eras 3-4, 8000 BCE to 500 CE | G49: Africa | H49: trade, travel and exchange | I49: existing + new | J49: Phase 2 | K49: 1 | L49: 3 | M49: =K49+L49 -> 4 | N49: H5.4, H6.7 | O49: WHFUA Big Era 4, Landscape 4.1 | P49: phoenicians-alphabet | Q49: By level: 5: 2 new; 6: 1 new, 1 existing. Carthage lay in today's Tunisia; the existing Phoenician card is counted as Middle East. Carthage is named on phoenicians card 3, so answers are Hanno, Hannibal or the harbour, not Carthage. Phase 2.
A50: T4-6-018 | B50: Tier 4-6 | C50: 5, 6 | D50: Ancient Israel and Judaism | E50: The Hebrew Bible, belief in one God, exile in Babylon, Torah and synagogue. | F50: Big Era 4, 1200 BCE to 500 CE | G50: Middle East | H50: belief and ideas | I50: new | J50: Phase 1 | K50: 0 | L50: 6 | M50: =K50+L50 -> 6 | N50: H5.6, H6.3 | O50: NCHS World History Era 3, Standard 1; Tanzania History A-level 2023, Form V | Q50: By level: 5: 4 new; 6: 2 new. A gap: in the existing cards Jews appear mostly as victims. Abraham, Moses and the Exodus are told as tradition and belief; archaeology confirms the kingdoms of Israel and Judah and the exile. Phase 1.
A51: T4-6-019 | B51: Tier 4-6 | C51: 5, 6 | D51: Hinduism, Jainism and the Vedic tradition | E51: The Vedas, dharma and karma, the epics, Mahavira, caste as history. | F51: Big Era 4, 1200 BCE to 500 CE | G51: Asia and Pacific | H51: belief and ideas | I51: new | J51: Phase 2 | K51: 0 | L51: 6 | M51: =K51+L51 -> 6 | N51: H5.6, H6.3 | O51: NCHS World History Era 3, Standard 3; NCERT Exploring Society Grade 6, cultural roots | Q51: By level: 5: 4 new; 6: 2 new. A gap in the existing sets. Belief marked as belief. Phase 2.
A52: T4-6-020 | B52: Tier 4-6 | C52: 5, 6 | D52: Work, families and slavery in the ancient world | E52: Farmers, crafts, women and children, slavery, serfdom and free work compared. | F52: Big Eras 3-4, 8000 BCE to 500 CE | G52: Global | H52: people and everyday life | I52: new | J52: Phase 2 | K52: 0 | L52: 7 | M52: =K52+L52 -> 7 | N52: H5.3, H6.2 | O52: WHFUA key theme Haves and Have-Nots; BNCC EF06HI17 | Q52: By level: 5: 4 new; 6: 3 new. The history of the 99 percent. Phase 2.
A53: T4-6-021 | B53: Tier 4-6 | C53: 5, 6 | D53: Persia: the Achaemenid empire | E53: Cyrus, Darius, the Royal Road, the Cyrus Cylinder, Persepolis, Ahuramazda in royal inscriptions. | F53: Big Era 4, 1200 BCE to 500 CE | G53: Middle East | H53: power and government | I53: new | J53: Phase 2 | K53: 0 | L53: 6 | M53: =K53+L53 -> 6 | N53: H5.5, H6.1 | O53: WHFUA Big Era 4, Landscape 4.4 | Q53: By level: 5: 2 new; 6: 4 new. A gap: Persia now appears only as Alexander's enemy. Persia is named on several existing cards, so answers are people, places or things such as Darius or the Royal Road. The Cyrus Cylinder praises Cyrus and tells how he returned gods and peoples to their homes; never call it the first human rights charter. Whether the kings were Zoroastrian is debated, so mark it as belief and as uncertain. Phase 2.
A54: T4-6-022 | B54: Tier 4-6 | C54: 6 | D54: Ancient Greece and the Olympic Games | E54: Sparta, the Persian wars, Herodotus, Hippocrates. | F54: Big Era 4, 1200 BCE to 500 CE | G54: Europe | H54: power and government | I54: existing + new | J54: Phase 2 | K54: 2 | L54: 4 | M54: =K54+L54 -> 6 | N54: H6.2, H6.7 | O54: NCHS World History Era 3, 2A; England National Curriculum 2013, KS2, Ancient Greece | P54: ancient-greece, olympic-games | Q54: By level: 6: 4 new, 2 existing. City-states, democracy and theatre are on the existing cards. No Olympic rings. Phase 2.
A55: T4-6-023 | B55: Tier 4-6 | C55: 6 | D55: Socrates, Plato and Aristotle | E55: One simple card each on Socrates, Plato and Aristotle. | F55: Big Era 4, 1200 BCE to 500 CE | G55: Europe | H55: belief and ideas | I55: existing | J55: Existing only | K55: 3 | L55: 0 | M55: =K55+L55 -> 3 | N55: H6.7 | O55: NCHS World History Era 3, Standard 2 | P55: socrates, plato, aristotle | Q55: By level: 6: 3 existing.
A56: T4-6-024 | B56: Tier 4-6 | C56: 6 | D56: Alexander the Great | E56: One simple card on Alexander the Great. | F56: Big Era 4, 1200 BCE to 500 CE | G56: Europe | H56: power and government | I56: existing | J56: Existing only | K56: 1 | L56: 0 | M56: =K56+L56 -> 1 | N56: H6.1, H6.7 | O56: NCHS World History Era 3, Standard 2 | P56: alexander-the-great | Q56: By level: 6: 1 existing.
A57: T4-6-025 | B57: Tier 4-6 | C57: 6 | D57: Archimedes and the scholars of Alexandria | E57: Euclid and the idea of proof, Eratosthenes measures the Earth, Hypatia, Hero's steam toy. | F57: Big Era 4, 1200 BCE to 500 CE | G57: Europe | H57: science, technology and mathematics | I57: existing + new | J57: Phase 1 | K57: 1 | L57: 6 | M57: =K57+L57 -> 7 | N57: H6.6, H6.7 | O57: NCHS World History Era 3, Standard 2; WHFUA Big Era 4, Landscape 4.4 | P57: archimedes | Q57: By level: 6: 6 new, 1 existing. The library of Alexandria is on an existing card. If a card mentions it: the library shrank over centuries, with no single great fire. Hypatia was killed in 415 in a political feud; her death did not end ancient science. Planned topics #60, #70 on the Akelius topic list. Phase 1.
A58: T4-6-026 | B58: Tier 4-6 | C58: 5, 6 | D58: Confucius, Laozi and the Hundred Schools | E58: Laozi and Daoism, Mencius, Mozi, the Legalists. | F58: Big Era 4, 1200 BCE to 500 CE | G58: Asia and Pacific | H58: belief and ideas | I58: existing + new | J58: Phase 2 | K58: 1 | L58: 4 | M58: =K58+L58 -> 5 | N58: H5.6, H6.7 | O58: WHFUA Big Era 4, Landscape 4.2 | P58: confucius | Q58: By level: 5: 3 new; 6: 1 new, 1 existing. Confucian rule is on the existing cards. Phase 2.
A59: T4-6-027 | B59: Tier 4-6 | C59: 5, 6 | D59: The Buddha and Buddhism in the Himalaya | E59: Guru Rinpoche and Taktsang, Songtsen Gampo and the first temples of Tibet and Bhutan, Mahayana and Theravada. | F59: Big Eras 4-5, 1200 BCE to 1500 CE | G59: Asia and Pacific | H59: belief and ideas | I59: existing + new | J59: Phase 1 | K59: 1 | L59: 6 | M59: =K59+L59 -> 7 | N59: H5.6, H6.3, H6.7 | O59: NCHS World History Era 4, 1B; Bhutan Social Studies 2025, Class IV; Bhutan History Framework 2022, Class VIII | P59: siddhartha-gautama | Q59: By level: 5: 2 new; 6: 4 new, 1 existing. The first cards that name Bhutan. Bhutanese tradition says Guru Rinpoche came in the 700s; the story of his flight to Taktsang is marked as tradition, and so is the founding of the first temples. Phase 1.
A60: T4-6-028 | B60: Tier 4-6 | C60: 5, 6 | D60: Rome: republic and empire | E60: Pompeii, Spartacus, Leptis Magna in Roman Africa, Roman women and families. | F60: Big Era 4, 1200 BCE to 500 CE | G60: Europe | H60: power and government | I60: existing + new | J60: Phase 2 | K60: 3 | L60: 4 | M60: =K60+L60 -> 7 | N60: H5.3, H6.1, H6.2, H6.7 | O60: NCHS World History Era 3, 3A; NCERT Themes in World History Class 11, An Empire Across Three Continents | P60: roman-republic-empire, julius-caesar, augustus | Q60: By level: 5: 2 new; 6: 2 new, 3 existing. Roads, aqueducts and citizens are on the existing cards. Phase 2.
A61: T4-6-029 | B61: Tier 4-6 | C61: 6 | D61: Jesus and the spread of Christianity | E61: Early communities, Paul's journeys, Constantine's freedom of worship in 313, Theodosius makes it the state religion in 380, Armenia's early church. | F61: Big Era 4, 1200 BCE to 500 CE | G61: Middle East | H61: belief and ideas | I61: existing + new | J61: Phase 2 | K61: 1 | L61: 4 | M61: =K61+L61 -> 5 | N61: H6.3, H6.7 | O61: NCHS World History Era 3, Standard 3, and Era 4, 1B | P61: jesus-of-nazareth | Q61: By level: 6: 4 new, 1 existing. Jesus only from afar or from behind. Belief marked as belief. Aksum belongs to T4-6-033. Phase 2.
A62: T4-6-030 | B62: Tier 4-6 | C62: 5, 6 | D62: Ashoka, the Maurya and the Gupta age | E62: Decimal place value in the Gupta age, Aryabhata in 499, Nalanda, the iron pillar of Delhi, and after the Gupta age Brahmagupta's rules for zero in 628. | F62: Big Era 4, 1200 BCE to 500 CE | G62: Asia and Pacific | H62: science, technology and mathematics | I62: existing + new | J62: Phase 1 | K62: 1 | L62: 6 | M62: =K62+L62 -> 7 | N62: H5.5, H6.1, H6.6, H6.7 | O62: NCHS World History Era 4, 1C; NCERT Exploring Society Grade 7, the Gupta era | P62: ashoka | Q62: By level: 5: 2 new; 6: 4 new, 1 existing. Ashoka's edicts are on the existing cards. Brahmagupta worked after the Gupta empire fell. Planned topic #63 on the Akelius topic list. Phase 1.
A63: T4-6-031 | B63: Tier 4-6 | C63: 5, 6 | D63: The first emperor and Han China | E63: Liu Bang and Han rule, officials chosen by recommendation and trained at the Imperial Academy, Zhang Heng's earthquake detector, the historian Ban Zhao. | F63: Big Era 4, 1200 BCE to 500 CE | G63: Asia and Pacific | H63: power and government | I63: existing + new | J63: Phase 2 | K63: 1 | L63: 5 | M63: =K63+L63 -> 6 | N63: H5.3, H6.1, H6.6, H6.7 | O63: WHFUA Big Era 4, Landscapes 4.2 and 4.5 | P63: qin-shi-huangdi | Q63: By level: 5: 2 new; 6: 3 new, 1 existing. Han China is a gap in the existing sets. Written exams for officials start under the Sui and Tang and belong to T7-9-007. Paper was in use in the 100s BCE and improved by Cai Lun in 105 CE; the paper card itself is in T1-3-016. Sima Qian is named on qin card 5, so he is never an answer. Phase 2.
A64: T4-6-032 | B64: Tier 4-6 | C64: 6 | D64: The Silk Road | E64: Sogdian merchants and their letters, paper known in Central Asia before Islam. | F64: Big Eras 4-5, 1200 BCE to 1500 CE | G64: Asia and Pacific | H64: trade, travel and exchange | I64: existing + new | J64: Phase 2 | K64: 1 | L64: 2 | M64: =K64+L64 -> 3 | N64: H6.4, H6.7 | O64: WHFUA Big Era 4, Landscape 4.5 | P64: silk-road | Q64: By level: 6: 2 new, 1 existing. Envoys, silk, horses, Buddhism, Samarkand and Chang'an are on the existing cards. The story that prisoners from the battle of Talas in 751 brought papermaking west is a later legend; silk-road card 3 tells it as 'a story says', and a new card tests it only as a myth. Phase 2.
A65: T4-6-033 | B65: Tier 4-6 | C65: 5, 6 | D65: Aksum | E65: Obelisks, coins, a Christian kingdom, Red Sea trade with India. | F65: Big Era 4, 1200 BCE to 500 CE | G65: Africa | H65: trade, travel and exchange | I65: planned | J65: Phase 1 | K65: 0 | L65: 6 | M65: =K65+L65 -> 6 | N65: H5.5, H6.1, H6.3 | O65: NCHS World History Era 3, 1C; WHFUA Big Era 4, Landscape 4.3; Kenya KICD Senior School Grade 10 | Q65: By level: 5: 2 new; 6: 4 new. Aksum belongs to this row. The Queen of Sheba and the Ark of the Covenant are told as legend from the Kebra Nagast. Planned topic #90 on the Akelius topic list. Phase 1.
A66: T4-6-034 | B66: Tier 4-6 | C66: 5, 6 | D66: The Bantu expansion, iron and the Nok | E66: Bantu-speaking farmers spread from near today's Cameroon and mixed with other peoples; iron working; the Nok of Nigeria, a different people; Swahili's language family; Nilotes and Cushites. | F66: Big Era 4, 1200 BCE to 500 CE | G66: Africa | H66: people and everyday life | I66: new | J66: Phase 1 | K66: 0 | L66: 10 | M66: =K66+L66 -> 10 | N66: H5.4, H6.5 | O66: NCHS World History Era 4, 5A; WHFUA Big Era 4, Landscape 4.3; Tanzania HTM Form I 2023 | Q66: By level: 5: 3 new; 6: 7 new. Local for Tanzania. Tanzanian syllabi say migration; cards explain both words, migration and gradual spread. Phase 1.
A67: T4-6-035 | B67: Tier 4-6 | C67: 4, 6 | D67: First Australians and Pacific voyagers | E67: Aboriginal Australians and their 65,000-year story, Lapita sailors and their pottery. | F67: Big Eras 2-4, 200,000 years ago to 500 CE | G67: Asia and Pacific | H67: trade, travel and exchange | I67: new | J67: Phase 1 | K67: 0 | L67: 5 | M67: =K67+L67 -> 5 | N67: H4.3, H6.4 | O67: WHFUA Big Era 2, Landscape 2.1; WHFUA Big Era 3, Landscape 3.6 | Q67: By level: 4: 2 new; 6: 3 new. WHFUA Landscape 3.6 is still in development. Lapita belongs to this row; later Polynesian voyages belong to T7-9-020. Phase 1.
A68: T4-6-036 | B68: Tier 4-6 | C68: 6 | D68: The first coins | E68: Lydian coins, Chinese spade coins, Indian punch-marked coins. | F68: Big Era 4, 1200 BCE to 500 CE | G68: Global | H68: trade, travel and exchange | I68: new | J68: Phase 2 | K68: 0 | L68: 3 | M68: =K68+L68 -> 3 | N68: H6.6 | O68: WHFUA key theme Economic Networks and Exchange | Q68: By level: 6: 3 new. Cowries and markets belong to T1-3-018. The level-3 coin card there shows what coins were for; these cards say where they began. Phase 2.
A69: T4-6-037 | B69: Tier 4-6 | C69: 6 | D69: The Maya | E69: The ball game, Lady Six Sky of Naranjo, raised fields. | F69: Big Eras 4-5, 1200 BCE to 1500 CE | G69: Latin America | H69: people and everyday life | I69: existing + new | J69: Phase 2 | K69: 1 | L69: 3 | M69: =K69+L69 -> 4 | N69: H6.7 | O69: NCHS World History Era 4, Standard 6; WHFUA Big Era 4, Landscape 4.6 | P69: maya | Q69: By level: 6: 3 new, 1 existing. City-states, maize, the calendar, zero and glyphs are on the existing cards. Phase 2.
A70: T4-6-038 | B70: Tier 4-6 | C70: 5 | D70: Traditional leadership in Africa and Asia | E70: Councils of elders, Maasai age sets, Nyamwezi chiefdoms, Buganda's kabaka and council, Bhutan's village leaders. | F70: Across time | G70: Africa | H70: power and government | I70: new | J70: Phase 1 | K70: 0 | L70: 6 | M70: =K70+L70 -> 6 | N70: H5.8 | O70: WHFUA key theme Uses and Abuses of Power; Kenya KICD Upper Primary Grades 5 and 6; Tanzania HTM primary 2023, Std IV | Q70: By level: 5: 6 new. Each example gets a century, and cards say that colonial rule changed or created some chiefships. Also Asia: Bhutan. Phase 1.
A71: T4-6-039 | B71: Tier 4-6 | C71: 6 | D71: First look: the medieval world | E71: One simple card each on Muhammad, Byzantium, the Vikings, the Crusades, the Black Death, Genghis Khan, Joan of Arc, al-Khwarizmi, Ibn Sina, the House of Wisdom, Ibn Battuta, Mansa Musa, the Swahili coast, Zheng He, the Aztecs and the Inca. | F71: Big Era 5, 300-1500 CE | G71: Global | H71: time and evidence | I71: existing | J71: Existing only | K71: 16 | L71: 0 | M71: =K71+L71 -> 16 | N71: H6.7 | O71: WHFUA Panorama, Big Era 5; NCHS Historical Thinking Standard 1 | P71: muhammad, byzantine-empire, vikings, crusades, black-death, genghis-khan, joan-of-arc, al-khwarizmi, ibn-sina, house-of-wisdom, ibn-battuta, mansa-musa, swahili-coast, zheng-he, aztecs, inca | Q71: By level: 6: 16 existing. Depth follows at level 7.
A72: T4-6-040 | B72: Tier 4-6 | C72: 6 | D72: First look: the early modern world | E72: One simple card each on the Renaissance, Leonardo, Gutenberg, Columbus, Magellan, Copernicus, Galileo, Newton, the Reformation, Luther, Akbar, the Ottoman Empire, the transatlantic slave trade and the Enlightenment. | F72: Big Era 6, 1400-1800 | G72: Global | H72: time and evidence | I72: existing | J72: Existing only | K72: 14 | L72: 0 | M72: =K72+L72 -> 14 | N72: H6.7 | O72: WHFUA Panorama, Big Era 6; NCHS Historical Thinking Standard 1 | P72: renaissance, leonardo-da-vinci, johannes-gutenberg, christopher-columbus, ferdinand-magellan, nicolaus-copernicus, galileo-galilei, isaac-newton, protestant-reformation, martin-luther, akbar, ottoman-empire, transatlantic-slave-trade, the-enlightenment | Q72: By level: 6: 14 existing. Depth follows at level 8.
A73: T4-6-041 | B73: Tier 4-6 | C73: 6 | D73: First look: revolutions, industry and empire | E73: One simple card each on the American and French revolutions, Washington, Napoleon, Haiti, Bolivar, the Industrial Revolution, Darwin, Pasteur, Nightingale, Marx, the Meiji Restoration and the Scramble for Africa. | F73: Big Era 7, 1750-1914 | G73: Global | H73: time and evidence | I73: existing | J73: Existing only | K73: 13 | L73: 0 | M73: =K73+L73 -> 13 | N73: H6.7, H6.8 | O73: WHFUA Panorama, Big Era 7; NCHS Historical Thinking Standard 1 | P73: american-revolution, george-washington, french-revolution, napoleon-bonaparte, haitian-revolution, simon-bolivar, industrial-revolution, charles-darwin, louis-pasteur, florence-nightingale, karl-marx, meiji-restoration, scramble-for-africa | Q73: By level: 6: 13 existing. Depth follows at level 9.
A74: T4-6-042 | B74: Tier 4-6 | C74: 6 | D74: First look: the twentieth century | E74: One simple card each on the two world wars, Hitler, Churchill, Gandhi, Einstein, Curie, Turing, the United Nations, the Cold War, the Berlin Wall, the Moon landing, King, Mandela, African independence and Borlaug. | F74: Big Eras 8-9, 1900 to today | G74: Global | H74: time and evidence | I74: existing | J74: Existing only | K74: 16 | L74: 0 | M74: =K74+L74 -> 16 | N74: H6.7, H6.8 | O74: WHFUA Panorama, Big Eras 8 and 9; NCHS Historical Thinking Standard 1 | P74: world-war-i, adolf-hitler, world-war-ii, winston-churchill, mahatma-gandhi, albert-einstein, marie-curie, alan-turing, united-nations, cold-war, fall-of-the-berlin-wall, first-moon-landing, martin-luther-king, nelson-mandela, african-independence, norman-borlaug | Q74: By level: 6: 16 existing. Depth follows at levels 10 and 11.
A75: T4-6-043 | B75: Tier 4-6 | C75: 6 | D75: First look: Africa from Lalibela to independence | E75: Lalibela, Great Zimbabwe, Benin City, Queen Nzinga, Mkwawa of the Hehe, the Maji Maji war, Nyerere's Tanganyika. | F75: Big Eras 5-9, 300 CE to today | G75: Africa | H75: time and evidence | I75: new | J75: Phase 2 | K75: 0 | L75: 9 | M75: =K75+L75 -> 9 | N75: H6.7, H6.8 | O75: WHFUA Panorama units, Big Eras 5-9; Tanzania HTM primary 2023, Std V and VI | Q75: By level: 6: 9 new. Added so that level 6 is not mostly Europe. Each card takes a facet the owning row at a later level does not use. Timbuktu, Adwa and Tanganyika in 1961 are named on existing cards, so they are context, not answers. Phase 2.
A76: T4-6-044 | B76: Tier 4-6 | C76: 6 | D76: First look: Asia | E76: Tang block printing, Sejong's hangul, Angkor, Hampi in Vijayanagara, the Zhabdrung unites Bhutan, the long Tokugawa peace, the Opium War, Sukarno and Indonesia's independence. | F76: Big Eras 5-9, 300 CE to today | G76: Asia and Pacific | H76: time and evidence | I76: new | J76: Phase 2 | K76: 0 | L76: 8 | M76: =K76+L76 -> 8 | N76: H6.7, H6.8 | O76: WHFUA Panorama units, Big Eras 5-9; Bhutan Social Studies 2025, Class V | Q76: By level: 6: 8 new. Added so that level 6 is not mostly Europe. Each card takes a facet the owning row does not use. No script in images. Phase 2.
A77: T4-6-045 | B77: Tier 4-6 | C77: 6 | D77: First look: Latin America and the Middle East | E77: Potosi's silver mountain, Palmares, Mexico's land and liberty, the Suez Canal of 1869, Isfahan's great square. | F77: Big Eras 6-8, 1400-1950 | G77: Latin America | H77: time and evidence | I77: new | J77: Phase 2 | K77: 0 | L77: 5 | M77: =K77+L77 -> 5 | N77: H6.7, H6.8 | O77: WHFUA Panorama units, Big Eras 6-8; BNCC 7th year | Q77: By level: 6: 5 new. Also Middle East. Each card takes a facet the owning row does not use. Phase 2.
A78: T4-6-046 | B78: Tier 4-6 | C78: 5, 6 | D78: African and local religions as history | E78: Ancestors and spirits, Yoruba orisha, Bon and local deities in Bhutan, Shinto, how missionaries and colonial rulers described them. | F78: Across time | G78: Africa | H78: belief and ideas | I78: new | J78: Phase 2 | K78: 0 | L78: 6 | M78: =K78+L78 -> 6 | N78: H5.6, H6.3 | O78: WHFUA key theme Spiritual Life and Moral Codes; Tanzania History A-level 2023, Form V, religion and the state; Bhutan History Framework 2022, Class VIII; Tanzania HTM primary 2023, Std III | Q78: By level: 5: 3 new; 6: 3 new. Added because African and local religions had no row. Belief as belief; no secret sacred objects. Also Asia. Phase 2.
A79: T7-9-001 | B79: Tier 7-9 | C79: 7, 9 | D79: Byzantium and Kievan Rus | E79: Cyril and Methodius, Vladimir's choice of faith in 988, Empress Theodora. | F79: Big Era 5, 300-1500 CE | G79: Europe | H79: power and government | I79: existing + new | J79: Phase 2 | K79: 1 | L79: 3 | M79: =K79+L79 -> 4 | N79: H7.8, H9.7 | O79: NCHS World History Era 4, 2C | P79: byzantine-empire | Q79: By level: 7: 3 new; 9: 1 existing. Rus trade with Constantinople is on an existing Viking card. No letters in images. Phase 2.
A80: T7-9-002 | B80: Tier 7-9 | C80: 7, 9 | D80: Muhammad, the caliphates and the spread of Islam | E80: The Sasanian empire that Islam replaced, Umayyads, Abbasids, Sunni and Shia, Islam carried by traders to Africa and Asia. | F80: Big Era 5, 300-1500 CE | G80: Middle East | H80: belief and ideas | I80: existing + new | J80: Phase 1 | K80: 1 | L80: 8 | M80: =K80+L80 -> 9 | N80: H7.1, H9.7 | O80: NCHS World History Era 4, 2A and Standard 2; WHFUA Big Era 5, Landscape 5.2 | P80: muhammad | Q80: By level: 7: 8 new; 9: 1 existing. Muhammad is never shown; no calligraphy. Belief marked as belief. Cordoba and al-Andalus belong to T7-9-003. Phase 1.
A81: T7-9-003 | B81: Tier 7-9 | C81: 7, 9 | D81: Baghdad, Cordoba and Islamic scholars | E81: Cordoba and al-Andalus, Maimonides, Ibn Khaldun, Rumi. | F81: Big Era 5, 300-1500 CE | G81: Middle East | H81: science, technology and mathematics | I81: existing + new | J81: Phase 1 | K81: 3 | L81: 6 | M81: =K81+L81 -> 9 | N81: H7.1, H9.7 | O81: NCHS World History Era 4, Standard 2; WHFUA Big Era 5, Landscape 5.2; England National Curriculum 2013, KS2, Baghdad c. AD 900 | P81: al-khwarizmi, ibn-sina, house-of-wisdom | Q81: By level: 7: 6 new; 9: 3 existing. Ibn Rushd is named on aristotle card 5, so he is context only. No calligraphy. Planned topics #73, #117 on the Akelius topic list. Phase 1.
A82: T7-9-004 | B82: Tier 7-9 | C82: 9 | D82: The Vikings | E82: One card on the Vikings at level 9. | F82: Big Era 5, 300-1500 CE | G82: Europe | H82: trade, travel and exchange | I82: existing | J82: Existing only | K82: 1 | L82: 0 | M82: =K82+L82 -> 1 | N82: H9.7 | O82: NCHS World History Era 4, Standard 4 | P82: vikings | Q82: By level: 9: 1 existing. No horned helmets.
A83: T7-9-005 | B83: Tier 7-9 | C83: 7, 9 | D83: Medieval Europe: lords, peasants, nuns, monks and towns | E83: Manor and serfs, women's work on the land, guilds, universities, Hildegard of Bingen, Christine de Pizan, Charlemagne, Magna Carta. | F83: Big Era 5, 300-1500 CE | G83: Europe | H83: people and everyday life | I83: existing + new | J83: Phase 1 | K83: 1 | L83: 8 | M83: =K83+L83 -> 9 | N83: H7.2, H9.7 | O83: NCHS World History Era 5, Standard 2; NCERT Themes in World History Class 11, The Three Orders; Bhutan History Framework 2022, Class VII, feudalism | P83: joan-of-arc | Q83: By level: 7: 8 new; 9: 1 existing. Women make up at least a third of the people named. Planned topics #118, #119 on the Akelius topic list. Phase 1.
A84: T7-9-006 | B84: Tier 7-9 | C84: 7, 9 | D84: The Crusades and Saladin | E84: Jerusalem in 1099 and 1187, Saladin and the truce of 1192, attacks on Jews in 1096, the sack of Constantinople in 1204, crusades in Spain and the Baltic, how Byzantines, Eastern Christians and Jews saw them. | F84: Big Era 5, 300-1500 CE | G84: Middle East | H84: conflict and peace | I84: existing + new | J84: Phase 1 | K84: 1 | L84: 4 | M84: =K84+L84 -> 5 | N84: H7.8, H9.7 | O84: NCHS World History Era 5, 2B; WHFUA Big Era 5, Landscape 5.3 | P84: crusades | Q84: By level: 7: 4 new; 9: 1 existing. Balanced, more than two sides. Trade across the sea and the two-books view are on existing crusades cards. No gore. Planned topic #115 on the Akelius topic list. Phase 1.
A85: T7-9-007 | B85: Tier 7-9 | C85: 7 | D85: Tang and Song China | E85: Wu Zetian, written exams for officials, block printing, gunpowder, the compass, paper money. | F85: Big Era 5, 300-1500 CE | G85: Asia and Pacific | H85: science, technology and mathematics | I85: new | J85: Phase 2 | K85: 0 | L85: 9 | M85: =K85+L85 -> 9 | N85: H7.4 | O85: NCHS World History Era 4, Standard 3, and Era 5, Standard 1; AP World History: Modern Unit 1, KC-3.1.I.D | Q85: By level: 7: 9 new. A gap in the existing sets. Written exams for officials begin under the Sui and Tang. No readable characters in images. Phase 2.
A86: T7-9-008 | B86: Tier 7-9 | C86: 7 | D86: Korea and Japan before 1600 | E86: Goryeo metal type, Sejong's hangul, Murasaki Shikibu, samurai. | F86: Big Era 5, 300-1500 CE | G86: Asia and Pacific | H86: belief and ideas | I86: planned | J86: Phase 1 | K86: 0 | L86: 8 | M86: =K86+L86 -> 8 | N86: H7.4 | O86: NCHS World History Era 4, Standard 3 | Q86: By level: 7: 8 new. Korea is a gap in the existing sets. No script in images. Planned topic #101 on the Akelius topic list. Phase 1.
A87: T7-9-009 | B87: Tier 7-9 | C87: 9 | D87: The Silk Road in its great age | E87: One card on the Silk Road at level 9. | F87: Big Era 5, 300-1500 CE | G87: Asia and Pacific | H87: trade, travel and exchange | I87: existing | J87: Existing only | K87: 1 | L87: 0 | M87: =K87+L87 -> 1 | N87: H9.7 | O87: WHFUA Big Era 5, Landscape 5.3 | P87: silk-road | Q87: By level: 9: 1 existing. New Silk Road cards are in T4-6-032, since Samarkand and Marco Polo are on existing cards. The Talas paper story is a later legend; paper was known in Central Asia before Islam and made in Baghdad by about 800.
A88: T7-9-010 | B88: Tier 7-9 | C88: 7, 9 | D88: Genghis Khan and the Mongol empires | E88: Kublai Khan and the Yuan, the failed invasions of Japan, the Golden Horde, Sorghaghtani Beki, Timur. | F88: Big Era 5, 300-1500 CE | G88: Asia and Pacific | H88: power and government | I88: existing + new | J88: Phase 2 | K88: 1 | L88: 6 | M88: =K88+L88 -> 7 | N88: H7.5, H9.7 | O88: WHFUA Big Era 5, Landscape 5.4; NCHS World History Era 5, Standard 3 | P88: genghis-khan | Q88: By level: 7: 6 new; 9: 1 existing. Marco Polo and Baghdad in 1258 are on existing cards. No gore. Phase 2.
A89: T7-9-011 | B89: Tier 7-9 | C89: 7, 9 | D89: The Black Death and the 1300s | E89: Plague from Central Asia, through the Golden Horde and Caffa to Cairo, Damascus and Europe; revolts after it; why we do not know if it reached China. | F89: Big Era 5, 300-1500 CE | G89: Europe | H89: people and everyday life | I89: existing + new | J89: Phase 2 | K89: 1 | L89: 3 | M89: =K89+L89 -> 4 | N89: H7.5, H9.7 | O89: WHFUA Big Era 5, Landscape 5.5; NCHS World History Era 5, Standard 5 | P89: black-death | Q89: By level: 7: 3 new; 9: 1 existing. Ancient DNA traces the strain of the 1340s to the Tian Shan area around 1338; Chinese records of the same years cannot be shown to be plague. Also Middle East and Asia. Phase 2.
A90: T7-9-012 | B90: Tier 7-9 | C90: 7, 9 | D90: Mali and the empires of West Africa | E90: The Ghana empire and Koumbi Saleh, Sundiata and the griots' epic, Kanem-Bornu, the mud mosque of Djenne, the Hausa city-states. | F90: Big Era 5, 300-1500 CE | G90: Africa | H90: trade, travel and exchange | I90: existing + new | J90: Phase 2 | K90: 1 | L90: 8 | M90: =K90+L90 -> 9 | N90: H7.3, H7.7, H9.7 | O90: NCHS World History Era 5, Standard 4; WHFUA Big Era 5, Landscape 5.3; AP World History: Modern Unit 1; Kenya KICD Senior School Grade 12 | P90: mansa-musa | Q90: By level: 7: 8 new; 9: 1 existing. Timbuktu, its manuscripts, Mali and Songhai are named on existing cards, so they are context, not answers. African-independence card 2 names modern Ghana, so the answer is 'the Ghana empire' or Koumbi Saleh. Phase 2.
A91: T7-9-013 | B91: Tier 7-9 | C91: 7, 9 | D91: The Swahili coast and the Indian Ocean | E91: Songo Mnara, Pate and Lamu, Swahili houses and daily life, the Kilwa Chronicle as a source. | F91: Big Era 5, 300-1500 CE | G91: Africa | H91: trade, travel and exchange | I91: existing + new | J91: Phase 1 | K91: 1 | L91: 6 | M91: =K91+L91 -> 7 | N91: H7.3, H7.7, H9.7 | O91: WHFUA Big Era 5, Landscape 5.3; NCHS World History Era 5, Standard 4; Tanzania History O-level 2023, Form II; Kenya KICD Junior School Grade 8 | P91: swahili-coast | Q91: By level: 7: 6 new; 9: 1 existing. Local for Tanzania. Dhows, the monsoon, Kilwa coins and Zanzibar are on existing cards; Kilwa and Zanzibar are never answers. Phase 1.
A92: T7-9-014 | B92: Tier 7-9 | C92: 7 | D92: Great Zimbabwe and southern Africa | E92: Mapungubwe, the stone walls, the gold trade, the false colonial claim about who built it. | F92: Big Era 5, 300-1500 CE | G92: Africa | H92: power and government | I92: planned | J92: Phase 1 | K92: 0 | L92: 6 | M92: =K92+L92 -> 6 | N92: H7.3, H7.7 | O92: NCHS World History Era 5, Standard 4; AP World History: Modern Unit 1; Kenya KICD Junior School Grade 7 | Q92: By level: 7: 6 new. Great Zimbabwe belongs to this row. Planned topic #91 on the Akelius topic list. Phase 1.
A93: T7-9-015 | B93: Tier 7-9 | C93: 7 | D93: Ethiopia and Lalibela | E93: Rock-cut churches and the highland kingdom. | F93: Big Era 5, 300-1500 CE | G93: Africa | H93: belief and ideas | I93: new | J93: Phase 2 | K93: 0 | L93: 5 | M93: =K93+L93 -> 5 | N93: H7.3 | O93: NCHS World History Era 5, Standard 4; Kenya KICD Junior School Grade 9, rock-hewn churches | Q93: By level: 7: 5 new. Lalibela belongs to this row. Ethiopia is named on existing cards, so answers are Lalibela or its king. Phase 2.
A94: T7-9-016 | B94: Tier 7-9 | C94: 7, 8 | D94: Ife, Benin and the forest kingdoms | E94: Ife heads, Benin's walls, the Oba, the bronze guilds, Oyo. | F94: Big Eras 5-6, 300 CE to 1800 | G94: Africa | H94: power and government | I94: new | J94: Phase 2 | K94: 0 | L94: 6 | M94: =K94+L94 -> 6 | N94: H7.3, H8.8 | O94: NCHS World History Era 5, Standard 4, and Era 6, Standard 4; England National Curriculum 2013, KS2, Benin; Kenya KICD Senior School Grade 12 | Q94: By level: 7: 4 new; 8: 2 new. The return of the Benin bronzes belongs to T10-U-007. Phase 2.
A95: T7-9-017 | B95: Tier 7-9 | C95: 9 | D95: Ibn Battuta | E95: One card on Ibn Battuta at level 9. | F95: Big Era 5, 300-1500 CE | G95: Africa | H95: trade, travel and exchange | I95: existing | J95: Existing only | K95: 1 | L95: 0 | M95: =K95+L95 -> 1 | N95: H9.7 | O95: WHFUA Big Era 5, Landscape 5.3; NCERT Themes in Indian History Class 12, travellers | P95: ibn-battuta | Q95: By level: 9: 1 existing. Counted as Africa.
A96: T7-9-018 | B96: Tier 7-9 | C96: 7 | D96: The Delhi Sultanate and Vijayanagara | E96: Delhi's sultans, the Mongols held off, Hampi. | F96: Big Era 5, 300-1500 CE | G96: Asia and Pacific | H96: power and government | I96: new | J96: Phase 2 | K96: 0 | L96: 5 | M96: =K96+L96 -> 5 | N96: H7.1 | O96: AP World History: Modern Unit 1; NCERT Themes in Indian History Class 12, Vijayanagara | Q96: By level: 7: 5 new. Factual and balanced. Delhi is named on an existing Ibn Battuta card, so answers are Vijayanagara, Hampi or a named sultan. Phase 2.
A97: T7-9-019 | B97: Tier 7-9 | C97: 7 | D97: Southeast Asia: Srivijaya to Dai Viet | E97: The Malacca strait, Borobudur, Angkor's water works, the Chola fleet of 1025, Majapahit, Islam in Java. | F97: Big Era 5, 300-1500 CE | G97: Asia and Pacific | H97: trade, travel and exchange | I97: planned | J97: Phase 1 | K97: 0 | L97: 8 | M97: =K97+L97 -> 8 | N97: H7.6 | O97: NCHS World History Era 4, Standard 3, and Era 5, 1B; AP World History: Modern Unit 1 | Q97: By level: 7: 8 new. Southeast Asia is a gap in the existing sets. Angkor belongs to this row. Planned topic #103 on the Akelius topic list. Phase 1.
A98: T7-9-020 | B98: Tier 7-9 | C98: 7 | D98: Polynesian navigators | E98: Stars, swells and birds; Hawaii, Aotearoa, Rapa Nui. | F98: Big Era 5, 300-1500 CE | G98: Asia and Pacific | H98: trade, travel and exchange | I98: new | J98: Phase 2 | K98: 0 | L98: 5 | M98: =K98+L98 -> 5 | N98: H7.6 | O98: NCHS World History Era 4, Standard 5 | Q98: By level: 7: 5 new. Settled about 1000-1200 for Hawaii and Rapa Nui and about 1250-1300 for Aotearoa. Avoid the story that the islanders destroyed their own island; the great losses on Rapa Nui came after the slave raids of 1862. Phase 2.
A99: T7-9-021 | B99: Tier 7-9 | C99: 7, 9 | D99: The Maya after the classic age | E99: Chichen Itza, Mayapan, Maya traders by canoe. | F99: Big Era 5, 300-1500 CE | G99: Latin America | H99: people and everyday life | I99: existing + new | J99: Phase 2 | K99: 1 | L99: 2 | M99: =K99+L99 -> 3 | N99: H7.6, H9.7 | O99: WHFUA Big Era 5, Landscape 5.6; NCHS World History Era 5, Standard 6 | P99: maya | Q99: By level: 7: 2 new; 9: 1 existing. Why the classic cities were left is on an existing Maya card. Phase 2.
A100: T7-9-022 | B100: Tier 7-9 | C100: 7 | D100: Cahokia and North America | E100: The mound city, Ancestral Puebloans. | F100: Big Era 5, 300-1500 CE | G100: North America | H100: people and everyday life | I100: new | J100: Phase 2 | K100: 0 | L100: 3 | M100: =K100+L100 -> 3 | N100: H7.6 | O100: NCHS World History Era 5, 6A; AP World History: Modern Unit 1, Cahokia | Q100: By level: 7: 3 new. Phase 2.
A101: T7-9-023 | B101: Tier 7-9 | C101: 7, 9 | D101: The Aztecs and Tenochtitlan | E101: Schools for every boy, Nezahualcoyotl the poet king, the Aztec herbal of 1552. | F101: Big Era 5, 300-1500 CE | G101: Latin America | H101: people and everyday life | I101: existing + new | J101: Phase 2 | K101: 1 | L101: 3 | M101: =K101+L101 -> 4 | N101: H7.6, H9.7 | O101: NCHS World History Era 5, Standard 6 | P101: aztecs | Q101: By level: 7: 3 new; 9: 1 existing. The market, floating gardens, tribute and the fall in 1521 are on existing cards. If conquest is mentioned: Tlaxcalan allies were most of the army, and the story that the Mexica took Cortes for Quetzalcoatl comes from later sources. No gore. Phase 2.
A102: T7-9-024 | B102: Tier 7-9 | C102: 7, 8, 9 | D102: The Inca and the earlier Andes | E102: Tiwanaku, Wari, Chimu and Chan Chan, mit'a labour before and after the conquest. | F102: Big Eras 5-6, 300 CE to 1800 | G102: Latin America | H102: power and government | I102: existing + new | J102: Phase 2 | K102: 1 | L102: 4 | M102: =K102+L102 -> 5 | N102: H7.6, H8.7, H9.7 | O102: NCHS World History Era 5, 6B; BNCC EF06HI08 | P102: inca | Q102: By level: 7: 3 new; 8: 1 new; 9: 1 existing. The quipu and rope bridges are on existing cards. Phase 2.
A103: T7-9-025 | B103: Tier 7-9 | C103: 7 | D103: Fibonacci and the numbers that reached Europe | E103: Indian numerals by way of Baghdad and North Africa, Fibonacci's book of 1202. | F103: Big Era 5, 300-1500 CE | G103: Europe | H103: science, technology and mathematics | I103: planned | J103: Phase 1 | K103: 0 | L103: 3 | M103: =K103+L103 -> 3 | N103: H7.8 | O103: WHFUA Big Era 5, Landscape 5.3 | Q103: By level: 7: 3 new. Never write Leonardo, the first name of another set's answer. Planned topic #64 on the Akelius topic list. Phase 1.
A104: T7-9-026 | B104: Tier 7-9 | C104: 9 | D104: Zheng He | E104: One card on Zheng He at level 9. | F104: Big Era 6, 1400-1800 | G104: Asia and Pacific | H104: trade, travel and exchange | I104: existing | J104: Existing only | K104: 1 | L104: 0 | M104: =K104+L104 -> 1 | N104: H9.7 | O104: WHFUA Big Era 6, Landscape 6.1 | P104: zheng-he | Q104: By level: 9: 1 existing.
A105: T7-9-027 | B105: Tier 7-9 | C105: 8, 9 | D105: The Renaissance | E105: Sofonisba Anguissola and Lavinia Fontana, Shakespeare, Durer and Erasmus. | F105: Big Era 6, 1400-1800 | G105: Europe | H105: belief and ideas | I105: existing + new | J105: Phase 1 | K105: 2 | L105: 4 | M105: =K105+L105 -> 6 | N105: H8.6, H9.7 | O105: NCHS World History Era 6, Standard 2; NCERT Themes in World History Class 11, Changing Cultural Traditions | P105: renaissance, leonardo-da-vinci | Q105: By level: 8: 4 new; 9: 2 existing. City-states and humanism are on existing cards. Planned topic #121 on the Akelius topic list. Phase 1.
A106: T7-9-028 | B106: Tier 7-9 | C106: 8, 9 | D106: Printing | E106: Print shops, the first newspapers, print in the Ottoman world from 1493 and 1727. | F106: Big Era 6, 1400-1800 | G106: Europe | H106: science, technology and mathematics | I106: existing + new | J106: Phase 2 | K106: 1 | L106: 2 | M106: =K106+L106 -> 3 | N106: H8.6, H9.7 | O106: NCHS World History Era 6, Standard 2; NCERT India and the Contemporary World II Class 10, Print Culture | P106: johannes-gutenberg | Q106: By level: 8: 2 new; 9: 1 existing. No sultan's ban on printing is proven: Jewish printers worked in Istanbul from 1493 and Muteferrika's press began in 1727. No Arabic script in images. Phase 2.
A107: T7-9-029 | B107: Tier 7-9 | C107: 8, 9 | D107: The age of ocean voyages | E107: Dias, da Gama and his pilot from Malindi, Cabral in Brazil, Elmina in 1482. | F107: Big Era 6, 1400-1800 | G107: Global | H107: trade, travel and exchange | I107: existing + new | J107: Phase 2 | K107: 2 | L107: 6 | M107: =K107+L107 -> 8 | N107: H8.1, H9.7 | O107: NCHS World History Era 6, Standard 1; WHFUA Big Era 6, Landscape 6.1; Tanzania History O-level 2023, Form II | P107: christopher-columbus, ferdinand-magellan | Q107: By level: 8: 6 new; 9: 2 existing. Told from the coasts too. The pilot from Malindi was probably a Gujarati; do not name Ibn Majid. The Portuguese at Kilwa and Mombasa are on an existing Swahili-coast card. Elmina belongs to this row. Phase 2.
A108: T7-9-030 | B108: Tier 7-9 | C108: 8 | D108: The Columbian Exchange | E108: Cassava to Africa, chilli peppers to Asia, horses on the American plains, smallpox, sugar, silver to China. | F108: Big Era 6, 1400-1800 | G108: Global | H108: trade, travel and exchange | I108: new | J108: Phase 1 | K108: 0 | L108: 7 | M108: =K108+L108 -> 7 | N108: H8.2 | O108: WHFUA Big Era 6, Landscape 6.2; Bhutan History Framework 2022, Class X | Q108: By level: 8: 7 new. A gap in the existing sets. Answers are crops, animals and diseases; the word Columbian never appears in clue text, since Columbus is another set's answer. Foods already on the Columbus cards are skipped. Phase 1.
A109: T7-9-031 | B109: Tier 7-9 | C109: 8 | D109: Spanish and Portuguese America | E109: Encomienda, Potosi, missions, castas, sugar, Palmares, Guaman Poma's letter to the king. | F109: Big Era 6, 1400-1800 | G109: Latin America | H109: empire and colonialism | I109: new | J109: Phase 1 | K109: 0 | L109: 7 | M109: =K109+L109 -> 7 | N109: H8.7 | O109: NCHS World History Era 6, Standard 4; BNCC 7th year, viceroyalties; IB DP new guide, Americas regional study 2, reference only | Q109: By level: 8: 7 new. Potosi and Palmares belong to this row. Phase 1.
A110: T7-9-032 | B110: Tier 7-9 | C110: 8, 9 | D110: The transatlantic slave trade | E110: Ouidah, revolts at sea, Queen Nanny's maroon towns in Jamaica, the regions captives came from. | F110: Big Era 6, 1400-1800 | G110: Global | H110: rights, freedom and equality | I110: existing + new | J110: Phase 2 | K110: 1 | L110: 4 | M110: =K110+L110 -> 5 | N110: H8.3, H9.7 | O110: NCHS World History Era 6, Standard 4; WHFUA Big Era 6, Landscape 6.5; BNCC EF07HI16 | P110: transatlantic-slave-trade | Q110: By level: 8: 4 new; 9: 1 existing. Plantations and Equiano are on existing cards; Equiano is context only. No gore. Phase 2.
A111: T7-9-033 | B111: Tier 7-9 | C111: 8, 9 | D111: East African and Indian Ocean slave trades | E111: Caravans to Bagamoyo, ivory and captives, the Saharan routes, the Zanzibar market closed in 1873. | F111: Big Eras 6-7, 1400-1914 | G111: Africa | H111: rights, freedom and equality | I111: new | J111: Phase 1 | K111: 0 | L111: 5 | M111: =K111+L111 -> 5 | N111: H8.3, H9.4 | O111: NCHS World History Era 6, Standard 4; Tanzania History O-level 2023, Form II; Kenya KICD Junior School Grades 7 and 8 | Q111: By level: 8: 3 new; 9: 2 new. Local and sensitive. The meaning of the name Bagamoyo is debated. Cloves and Omani rule on Zanzibar are on an existing Swahili-coast card. Phase 1.
A112: T7-9-034 | B112: Tier 7-9 | C112: 8 | D112: Africa 1450-1800 | E112: Queen Nzinga, the Kongo kings and their letters to Portugal, the fall of Songhai in 1591, Asante, Oyo, Dahomey, Ethiopia's Gondar. | F112: Big Era 6, 1400-1800 | G112: Africa | H112: power and government | I112: planned | J112: Phase 1 | K112: 0 | L112: 10 | M112: =K112+L112 -> 10 | N112: H8.8 | O112: NCHS World History Era 6, Standard 4; Kenya KICD Junior School Grade 7, Kongo | Q112: By level: 8: 10 new. Afonso I and Songhai are named on existing cards, so they are context, not answers. Planned topic #96 on the Akelius topic list. Phase 1.
A113: T7-9-035 | B113: Tier 7-9 | C113: 8, 9 | D113: The Ottoman Empire | E113: Hurrem Sultan, Piri Reis's map, Ottoman Egypt and the Hajj caravans, the traveller Evliya Celebi. | F113: Big Eras 6-7, 1400-1914 | G113: Middle East | H113: power and government | I113: existing + new | J113: Phase 2 | K113: 1 | L113: 4 | M113: =K113+L113 -> 5 | N113: H8.5, H9.7 | O113: NCHS World History Era 6, Standard 3; AP World History: Modern Unit 3 | P113: ottoman-empire | Q113: By level: 8: 3 new; 9: 1 new, 1 existing. Suleiman's laws, coffee houses, many faiths and the reforms are on existing cards. The map is never shown with writing. Phase 2.
A114: T7-9-036 | B114: Tier 7-9 | C114: 8 | D114: Safavid Persia and Isfahan | E114: Shah Abbas, Isfahan, silk, Shia Islam as the state faith. | F114: Big Era 6, 1400-1800 | G114: Middle East | H114: power and government | I114: new | J114: Phase 2 | K114: 0 | L114: 4 | M114: =K114+L114 -> 4 | N114: H8.5 | O114: WHFUA Big Era 6, Landscape 6.3 | Q114: By level: 8: 4 new. No calligraphy. Phase 2.
A115: T7-9-037 | B115: Tier 7-9 | C115: 8, 9 | D115: Akbar and the Mughal Empire | E115: Babur, Nur Jahan, Aurangzeb, Indian cotton. | F115: Big Era 6, 1400-1800 | G115: Asia and Pacific | H115: power and government | I115: existing + new | J115: Phase 2 | K115: 1 | L115: 5 | M115: =K115+L115 -> 6 | N115: H8.5, H9.7 | O115: NCHS World History Era 6, Standard 3; England National Curriculum 2013, KS3, Mughal India | P115: akbar | Q115: By level: 8: 5 new; 9: 1 existing. The Taj Mahal is on an existing Akbar card. Phase 2.
A116: T7-9-038 | B116: Tier 7-9 | C116: 8 | D116: Guru Nanak and the Sikh tradition | E116: One God and equality, the shared kitchen. | F116: Big Era 6, 1400-1800 | G116: Asia and Pacific | H116: belief and ideas | I116: new | J116: Phase 2 | K116: 0 | L116: 3 | M116: =K116+L116 -> 3 | N116: H8.5 | O116: WHFUA Big Era 6, Landscape 6.7; NCERT Understanding Society Grade 9 Part 2, Sikhs | Q116: By level: 8: 3 new. A gap in the existing sets. Belief marked as belief. Phase 2.
A117: T7-9-039 | B117: Tier 7-9 | C117: 8 | D117: Ming and Qing China | E117: The Forbidden City, porcelain and tea, silver, Qing expansion. | F117: Big Era 6, 1400-1800 | G117: Asia and Pacific | H117: power and government | I117: new | J117: Phase 2 | K117: 0 | L117: 5 | M117: =K117+L117 -> 5 | N117: H8.5 | O117: NCHS World History Era 6, Standard 3; England National Curriculum 2013, KS3, Qing China | Q117: By level: 8: 5 new. Ming is named on zheng-he card 5, so answers are places, things or rulers, not the dynasty's name. Phase 2.
A118: T7-9-040 | B118: Tier 7-9 | C118: 8 | D118: Tokugawa Japan and Joseon Korea | E118: The long peace, Edo, the turtle ships of the Imjin war. | F118: Big Era 6, 1400-1800 | G118: Asia and Pacific | H118: power and government | I118: new | J118: Phase 2 | K118: 0 | L118: 5 | M118: =K118+L118 -> 5 | N118: H8.8 | O118: NCHS World History Era 6, Standard 5 | Q118: By level: 8: 5 new. Phase 2.
A119: T7-9-041 | B119: Tier 7-9 | C119: 8 | D119: Bhutan unified under the Zhabdrung | E119: Pema Lingpa, the Zhabdrung's arrival in 1616 and unification over the next decades, dzongs, the dual system, never colonised. | F119: Big Era 6, 1400-1800 | G119: Asia and Pacific | H119: power and government | I119: planned | J119: Phase 1 | K119: 0 | L119: 6 | M119: =K119+L119 -> 6 | N119: H8.8 | O119: NCHS World History Era 6, Standard 5; Bhutan Social Studies 2025, Class V | Q119: By level: 8: 6 new. Neutral tone. Planned topic #105 on the Akelius topic list. Phase 1.
A120: T7-9-042 | B120: Tier 7-9 | C120: 8 | D120: European trading empires in Asia | E120: Goa, Malacca, the Dutch in Java and Batavia in 1619, the Manila galleons, Plassey in 1757. | F120: Big Era 6, 1400-1800 | G120: Asia and Pacific | H120: empire and colonialism | I120: new | J120: Phase 2 | K120: 0 | L120: 7 | M120: =K120+L120 -> 7 | N120: H8.7 | O120: AP World History: Modern Unit 4; NCERT Exploring Society Grade 8 Part I, chapter 4 | Q120: By level: 8: 7 new. A gap in the existing sets. Phase 2.
A121: T7-9-043 | B121: Tier 7-9 | C121: 8, 9 | D121: The Reformation and the wars of religion | E121: Catholic reform, the Thirty Years War, the peace of 1648. | F121: Big Era 6, 1400-1800 | G121: Europe | H121: belief and ideas | I121: existing + new | J121: Phase 2 | K121: 2 | L121: 3 | M121: =K121+L121 -> 5 | N121: H8.6, H9.7 | O121: NCHS World History Era 6, Standard 2; Tanzania History A-level 2023, Form VI, Westphalia | P121: protestant-reformation, martin-luther | Q121: By level: 8: 3 new; 9: 2 existing. Do not say Westphalia created modern sovereignty; that claim is a debate for level U. Phase 2.
A122: T7-9-044 | B122: Tier 7-9 | C122: 8 | D122: Absolute and limited monarchy | E122: Louis XIV, Elizabeth I, Peter the Great, the Bill of Rights of 1689. | F122: Big Era 6, 1400-1800 | G122: Europe | H122: power and government | I122: planned | J122: Phase 1 | K122: 0 | L122: 6 | M122: =K122+L122 -> 6 | N122: H8.4 | O122: NCHS World History Era 6, Standard 2 | Q122: By level: 8: 6 new. Daniel's own example outcome. Planned topics #120, #122 on the Akelius topic list. Phase 1.
A123: T7-9-045 | B123: Tier 7-9 | C123: 8, 9 | D123: The Scientific Revolution | E123: Vesalius, Kepler, Harvey, Descartes, the observatories of Samarkand and Istanbul. | F123: Big Era 6, 1400-1800 | G123: Europe | H123: science, technology and mathematics | I123: existing + new | J123: Phase 1 | K123: 3 | L123: 5 | M123: =K123+L123 -> 8 | N123: H8.6, H9.7 | O123: WHFUA Big Era 6, Landscape 6.6 | P123: nicolaus-copernicus, galileo-galilei, isaac-newton | Q123: By level: 8: 5 new; 9: 3 existing. The observatories outside Europe belong to this row. Planned topic #75 on the Akelius topic list. Phase 1.
A124: T7-9-046 | B124: Tier 7-9 | C124: 8, 9 | D124: Indigenous nations of North America | E124: The Haudenosaunee, the fur trade, the removals of the 1830s. | F124: Big Eras 6-7, 1400-1914 | G124: North America | H124: power and government | I124: new | J124: Phase 2 | K124: 0 | L124: 4 | M124: =K124+L124 -> 4 | N124: H8.7, H9.3 | O124: NCHS World History Era 6, Standard 4; NCERT Themes in World History Class 11, Displacing Indigenous Peoples | Q124: By level: 8: 2 new; 9: 2 new. Avoid the claim that the Haudenosaunee inspired the US constitution. Phase 2.
A125: T7-9-047 | B125: Tier 7-9 | C125: 9 | D125: The Enlightenment | E125: Wollstonecraft, Adam Smith, Anton Wilhelm Amo from the Gold Coast, Emilie du Chatelet. | F125: Big Eras 6-7, 1400-1914 | G125: Europe | H125: belief and ideas | I125: existing + new | J125: Phase 1 | K125: 1 | L125: 5 | M125: =K125+L125 -> 6 | N125: H9.1, H9.6 | O125: WHFUA Big Era 7, Landscape 7.2; Kenya KICD Senior School Grade 10, 3.1 | P125: the-enlightenment | Q125: By level: 9: 5 new, 1 existing. Wollstonecraft and Montesquieu are named on enlightenment cards 4 and 3. Wollstonecraft becomes an answer only if card 4 is rewritten in the same batch. Planned topics #77, #78 on the Akelius topic list. Phase 1.
A126: T7-9-048 | B126: Tier 7-9 | C126: 9 | D126: The American Revolution | E126: One card each on the American Revolution and George Washington at level 9. | F126: Big Era 7, 1750-1914 | G126: North America | H126: power and government | I126: existing | J126: Existing only | K126: 2 | L126: 0 | M126: =K126+L126 -> 2 | N126: H9.1, H9.7 | O126: NCHS World History Era 7, Standard 1 | P126: american-revolution, george-washington | Q126: By level: 9: 2 existing. The constitution and its first amendments are already on an existing card, so no new cards here.
...

Sheet Cards by level
A1: Topic ID | B1: Tier | C1: Topic | D1: L1 | E1: L2 | F1: L3 | G1: L4 | H1: L5 | I1: L6 | J1: L7 | K1: L8 | L1: L9 | M1: L10 | N1: L11 | O1: L12 | P1: U | Q1: Total | R1: Check
A2: T1-3-001 | B2: Tier 1-3 | C2: Time words, days and calendars | D2: 10 | Q2: =SUM(D2:P2) -> 10 | R2: =IF(Q2=Topics!M2,"ok","differs from Topics") -> ok
A3: T1-3-002 | B3: Tier 1-3 | C3: Children, families and school then and now | D3: 7 | E3: 5 | Q3: =SUM(D3:P3) -> 12 | R3: =IF(Q3=Topics!M3,"ok","differs from Topics") -> ok
A4: T1-3-003 | B4: Tier 1-3 | C4: Homes, tools and food through time | D4: 6 | E4: 4 | Q4: =SUM(D4:P4) -> 10 | R4: =IF(Q4=Topics!M4,"ok","differs from Topics") -> ok
A5: T1-3-004 | B5: Tier 1-3 | C5: Clues from the past | D5: 6 | E5: 4 | Q5: =SUM(D5:P5) -> 10 | R5: =IF(Q5=Topics!M5,"ok","differs from Topics") -> ok
A6: T1-3-005 | B6: Tier 1-3 | C6: Stories, songs and festivals | D6: 6 | E6: 4 | Q6: =SUM(D6:P6) -> 10 | R6: =IF(Q6=Topics!M6,"ok","differs from Topics") -> ok
A7: T1-3-006 | B7: Tier 1-3 | C7: Travel and messages, from feet to rockets | D7: 5 | E7: 3 | F7: 2 | Q7: =SUM(D7:P7) -> 10 | R7: =IF(Q7=Topics!M7,"ok","differs from Topics") -> ok
A8: T1-3-007 | B8: Tier 1-3 | C8: Leaders and rules: elders, chiefs and councils | D8: 6 | Q8: =SUM(D8:P8) -> 6 | R8: =IF(Q8=Topics!M8,"ok","differs from Topics") -> ok
A9: T1-3-008 | B9: Tier 1-3 | C9: Our oldest ancestors, in East Africa | E9: 8 | Q9: =SUM(D9:P9) -> 8 | R9: =IF(Q9=Topics!M9,"ok","differs from Topics") -> ok
A10: T1-3-009 | B10: Tier 1-3 | C10: Stone tools, fire and shelter | E10: 7 | Q10: =SUM(D10:P10) -> 7 | R10: =IF(Q10=Topics!M10,"ok","differs from Topics") -> ok
A11: T1-3-010 | B11: Tier 1-3 | C11: Hunting, fishing and gathering | E11: 6 | Q11: =SUM(D11:P11) -> 6 | R11: =IF(Q11=Topics!M11,"ok","differs from Topics") -> ok
A12: T1-3-011 | B12: Tier 1-3 | C12: Rock art and beads | E12: 6 | Q12: =SUM(D12:P12) -> 6 | R12: =IF(Q12=Topics!M12,"ok","differs from Topics") -> ok
A13: T1-3-012 | B13: Tier 1-3 | C13: People reach every continent | E13: 6 | Q13: =SUM(D13:P13) -> 6 | R13: =IF(Q13=Topics!M13,"ok","differs from Topics") -> ok
A14: T1-3-013 | B14: Tier 1-3 | C14: The first farmers and their crops | F14: 9 | Q14: =SUM(D14:P14) -> 9 | R14: =IF(Q14=Topics!M14,"ok","differs from Topics") -> ok
A15: T1-3-014 | B15: Tier 1-3 | C15: Taming animals | F15: 6 | Q15: =SUM(D15:P15) -> 6 | R15: =IF(Q15=Topics!M15,"ok","differs from Topics") -> ok
A16: T1-3-015 | B16: Tier 1-3 | C16: Villages, towns and the first cities | F16: 6 | Q16: =SUM(D16:P16) -> 6 | R16: =IF(Q16=Topics!M16,"ok","differs from Topics") -> ok
A17: T1-3-016 | B17: Tier 1-3 | C17: Writing, paper and counting | F17: 10 | Q17: =SUM(D17:P17) -> 10 | R17: =IF(Q17=Topics!M17,"ok","differs from Topics") -> ok
A18: T1-3-017 | B18: Tier 1-3 | C18: Wheels, boats, roads and bridges | F18: 6 | Q18: =SUM(D18:P18) -> 6 | R18: =IF(Q18=Topics!M18,"ok","differs from Topics") -> ok
A19: T1-3-018 | B19: Tier 1-3 | C19: Markets and money | E19: 3 | F19: 5 | Q19: =SUM(D19:P19) -> 8 | R19: =IF(Q19=Topics!M19,"ok","differs from Topics") -> ok
A20: T1-3-019 | B20: Tier 1-3 | C20: Great buildings and their builders | F20: 6 | Q20: =SUM(D20:P20) -> 6 | R20: =IF(Q20=Topics!M20,"ok","differs from Topics") -> ok
A21: T1-3-020 | B21: Tier 1-3 | C21: Long ago in Africa | F21: 8 | Q21: =SUM(D21:P21) -> 8 | R21: =IF(Q21=Topics!M21,"ok","differs from Topics") -> ok
A22: T1-3-021 | B22: Tier 1-3 | C22: Long ago in Asia | F22: 8 | Q22: =SUM(D22:P22) -> 8 | R22: =IF(Q22=Topics!M22,"ok","differs from Topics") -> ok
A23: T1-3-022 | B23: Tier 1-3 | C23: Long ago in the Americas | F23: 6 | Q23: =SUM(D23:P23) -> 6 | R23: =IF(Q23=Topics!M23,"ok","differs from Topics") -> ok
A24: T1-3-023 | B24: Tier 1-3 | C24: Long ago around the Mediterranean | F24: 5 | Q24: =SUM(D24:P24) -> 5 | R24: =IF(Q24=Topics!M24,"ok","differs from Topics") -> ok
A25: T1-3-024 | B25: Tier 1-3 | C25: Holy places in history | D25: 2 | E25: 2 | F25: 2 | Q25: =SUM(D25:P25) -> 6 | R25: =IF(Q25=Topics!M25,"ok","differs from Topics") -> ok
A26: T1-3-025 | B26: Tier 1-3 | C26: Famous journeys | F26: 4 | Q26: =SUM(D26:P26) -> 4 | R26: =IF(Q26=Topics!M26,"ok","differs from Topics") -> ok
A27: T1-3-026 | B27: Tier 1-3 | C27: People who changed the world | F27: 8 | Q27: =SUM(D27:P27) -> 8 | R27: =IF(Q27=Topics!M27,"ok","differs from Topics") -> ok
A28: T1-3-027 | B28: Tier 1-3 | C28: Keeping well: water, nurses and vaccines | F28: 6 | Q28: =SUM(D28:P28) -> 6 | R28: =IF(Q28=Topics!M28,"ok","differs from Topics") -> ok
A29: T1-3-028 | B29: Tier 1-3 | C29: Caring for land and forests | E29: 3 | F29: 3 | Q29: =SUM(D29:P29) -> 6 | R29: =IF(Q29=Topics!M29,"ok","differs from Topics") -> ok
A30: T1-3-029 | B30: Tier 1-3 | C30: Heritage near us: Tanzania | E30: 2 | F30: 2 | Q30: =SUM(D30:P30) -> 4 | R30: =IF(Q30=Topics!M30,"ok","differs from Topics") -> ok
A31: T1-3-030 | B31: Tier 1-3 | C31: Village life then and now: an East African homestead and a Himalayan farm | D31: 3 | E31: 3 | Q31: =SUM(D31:P31) -> 6 | R31: =IF(Q31=Topics!M31,"ok","differs from Topics") -> ok
A32: T1-3-031 | B32: Tier 1-3 | C32: Heritage near us: Bhutan | E32: 2 | F32: 2 | Q32: =SUM(D32:P32) -> 4 | R32: =IF(Q32=Topics!M32,"ok","differs from Topics") -> ok
A33: T4-6-001 | B33: Tier 4-6 | C33: The long timeline | G33: 4 | Q33: =SUM(D33:P33) -> 4 | R33: =IF(Q33=Topics!M33,"ok","differs from Topics") -> ok
A34: T4-6-002 | B34: Tier 4-6 | C34: How we know: sources, dates and timelines | G34: 4 | H34: 4 | Q34: =SUM(D34:P34) -> 8 | R34: =IF(Q34=Topics!M34,"ok","differs from Topics") -> ok
A35: T4-6-003 | B35: Tier 4-6 | C35: Human origins in Africa | G35: 12 | Q35: =SUM(D35:P35) -> 12 | R35: =IF(Q35=Topics!M35,"ok","differs from Topics") -> ok
A36: T4-6-004 | B36: Tier 4-6 | C36: Origin stories and what the evidence shows | G36: 5 | Q36: =SUM(D36:P36) -> 5 | R36: =IF(Q36=Topics!M36,"ok","differs from Topics") -> ok
A37: T4-6-005 | B37: Tier 4-6 | C37: Ice Age people and the peopling of the world | G37: 9 | Q37: =SUM(D37:P37) -> 9 | R37: =IF(Q37=Topics!M37,"ok","differs from Topics") -> ok
A38: T4-6-006 | B38: Tier 4-6 | C38: The farming revolution | G38: 12 | Q38: =SUM(D38:P38) -> 12 | R38: =IF(Q38=Topics!M38,"ok","differs from Topics") -> ok
A39: T4-6-007 | B39: Tier 4-6 | C39: The green Sahara and Africa's first farmers | G39: 6 | Q39: =SUM(D39:P39) -> 6 | R39: =IF(Q39=Topics!M39,"ok","differs from Topics") -> ok
A40: T4-6-008 | B40: Tier 4-6 | C40: Metals, wheels and horses | G40: 8 | Q40: =SUM(D40:P40) -> 8 | R40: =IF(Q40=Topics!M40,"ok","differs from Topics") -> ok
A41: T4-6-009 | B41: Tier 4-6 | C41: Ancient Egypt | H41: 4 | I41: 3 | Q41: =SUM(D41:P41) -> 7 | R41: =IF(Q41=Topics!M41,"ok","differs from Topics") -> ok
A42: T4-6-010 | B42: Tier 4-6 | C42: Mesopotamia and the first law codes | H42: 5 | I42: 2 | Q42: =SUM(D42:P42) -> 7 | R42: =IF(Q42=Topics!M42,"ok","differs from Topics") -> ok
A43: T4-6-011 | B43: Tier 4-6 | C43: The Indus valley civilisation | H43: 8 | Q43: =SUM(D43:P43) -> 8 | R43: =IF(Q43=Topics!M43,"ok","differs from Topics") -> ok
A44: T4-6-012 | B44: Tier 4-6 | C44: Early China: Shang and Zhou | H44: 6 | Q44: =SUM(D44:P44) -> 6 | R44: =IF(Q44=Topics!M44,"ok","differs from Topics") -> ok
A45: T4-6-013 | B45: Tier 4-6 | C45: How writing began around the world | H45: 2 | Q45: =SUM(D45:P45) -> 2 | R45: =IF(Q45=Topics!M45,"ok","differs from Topics") -> ok
A46: T4-6-014 | B46: Tier 4-6 | C46: Kush and Nubia | H46: 5 | I46: 2 | Q46: =SUM(D46:P46) -> 7 | R46: =IF(Q46=Topics!M46,"ok","differs from Topics") -> ok
A47: T4-6-015 | B47: Tier 4-6 | C47: Bronze Age Crete, Mycenae and the collapse | H47: 4 | Q47: =SUM(D47:P47) -> 4 | R47: =IF(Q47=Topics!M47,"ok","differs from Topics") -> ok
A48: T4-6-016 | B48: Tier 4-6 | C48: First civilisations of the Americas | H48: 8 | Q48: =SUM(D48:P48) -> 8 | R48: =IF(Q48=Topics!M48,"ok","differs from Topics") -> ok
A49: T4-6-017 | B49: Tier 4-6 | C49: The Phoenicians, Carthage and the voyage of Hanno | H49: 2 | I49: 2 | Q49: =SUM(D49:P49) -> 4 | R49: =IF(Q49=Topics!M49,"ok","differs from Topics") -> ok
A50: T4-6-018 | B50: Tier 4-6 | C50: Ancient Israel and Judaism | H50: 4 | I50: 2 | Q50: =SUM(D50:P50) -> 6 | R50: =IF(Q50=Topics!M50,"ok","differs from Topics") -> ok
A51: T4-6-019 | B51: Tier 4-6 | C51: Hinduism, Jainism and the Vedic tradition | H51: 4 | I51: 2 | Q51: =SUM(D51:P51) -> 6 | R51: =IF(Q51=Topics!M51,"ok","differs from Topics") -> ok
A52: T4-6-020 | B52: Tier 4-6 | C52: Work, families and slavery in the ancient world | H52: 4 | I52: 3 | Q52: =SUM(D52:P52) -> 7 | R52: =IF(Q52=Topics!M52,"ok","differs from Topics") -> ok
A53: T4-6-021 | B53: Tier 4-6 | C53: Persia: the Achaemenid empire | H53: 2 | I53: 4 | Q53: =SUM(D53:P53) -> 6 | R53: =IF(Q53=Topics!M53,"ok","differs from Topics") -> ok
A54: T4-6-022 | B54: Tier 4-6 | C54: Ancient Greece and the Olympic Games | I54: 6 | Q54: =SUM(D54:P54) -> 6 | R54: =IF(Q54=Topics!M54,"ok","differs from Topics") -> ok
A55: T4-6-023 | B55: Tier 4-6 | C55: Socrates, Plato and Aristotle | I55: 3 | Q55: =SUM(D55:P55) -> 3 | R55: =IF(Q55=Topics!M55,"ok","differs from Topics") -> ok
A56: T4-6-024 | B56: Tier 4-6 | C56: Alexander the Great | I56: 1 | Q56: =SUM(D56:P56) -> 1 | R56: =IF(Q56=Topics!M56,"ok","differs from Topics") -> ok
A57: T4-6-025 | B57: Tier 4-6 | C57: Archimedes and the scholars of Alexandria | I57: 7 | Q57: =SUM(D57:P57) -> 7 | R57: =IF(Q57=Topics!M57,"ok","differs from Topics") -> ok
A58: T4-6-026 | B58: Tier 4-6 | C58: Confucius, Laozi and the Hundred Schools | H58: 3 | I58: 2 | Q58: =SUM(D58:P58) -> 5 | R58: =IF(Q58=Topics!M58,"ok","differs from Topics") -> ok
A59: T4-6-027 | B59: Tier 4-6 | C59: The Buddha and Buddhism in the Himalaya | H59: 2 | I59: 5 | Q59: =SUM(D59:P59) -> 7 | R59: =IF(Q59=Topics!M59,"ok","differs from Topics") -> ok
A60: T4-6-028 | B60: Tier 4-6 | C60: Rome: republic and empire | H60: 2 | I60: 5 | Q60: =SUM(D60:P60) -> 7 | R60: =IF(Q60=Topics!M60,"ok","differs from Topics") -> ok
A61: T4-6-029 | B61: Tier 4-6 | C61: Jesus and the spread of Christianity | I61: 5 | Q61: =SUM(D61:P61) -> 5 | R61: =IF(Q61=Topics!M61,"ok","differs from Topics") -> ok
A62: T4-6-030 | B62: Tier 4-6 | C62: Ashoka, the Maurya and the Gupta age | H62: 2 | I62: 5 | Q62: =SUM(D62:P62) -> 7 | R62: =IF(Q62=Topics!M62,"ok","differs from Topics") -> ok
A63: T4-6-031 | B63: Tier 4-6 | C63: The first emperor and Han China | H63: 2 | I63: 4 | Q63: =SUM(D63:P63) -> 6 | R63: =IF(Q63=Topics!M63,"ok","differs from Topics") -> ok
A64: T4-6-032 | B64: Tier 4-6 | C64: The Silk Road | I64: 3 | Q64: =SUM(D64:P64) -> 3 | R64: =IF(Q64=Topics!M64,"ok","differs from Topics") -> ok
A65: T4-6-033 | B65: Tier 4-6 | C65: Aksum | H65: 2 | I65: 4 | Q65: =SUM(D65:P65) -> 6 | R65: =IF(Q65=Topics!M65,"ok","differs from Topics") -> ok
A66: T4-6-034 | B66: Tier 4-6 | C66: The Bantu expansion, iron and the Nok | H66: 3 | I66: 7 | Q66: =SUM(D66:P66) -> 10 | R66: =IF(Q66=Topics!M66,"ok","differs from Topics") -> ok
A67: T4-6-035 | B67: Tier 4-6 | C67: First Australians and Pacific voyagers | G67: 2 | I67: 3 | Q67: =SUM(D67:P67) -> 5 | R67: =IF(Q67=Topics!M67,"ok","differs from Topics") -> ok
A68: T4-6-036 | B68: Tier 4-6 | C68: The first coins | I68: 3 | Q68: =SUM(D68:P68) -> 3 | R68: =IF(Q68=Topics!M68,"ok","differs from Topics") -> ok
A69: T4-6-037 | B69: Tier 4-6 | C69: The Maya | I69: 4 | Q69: =SUM(D69:P69) -> 4 | R69: =IF(Q69=Topics!M69,"ok","differs from Topics") -> ok
A70: T4-6-038 | B70: Tier 4-6 | C70: Traditional leadership in Africa and Asia | H70: 6 | Q70: =SUM(D70:P70) -> 6 | R70: =IF(Q70=Topics!M70,"ok","differs from Topics") -> ok
A71: T4-6-039 | B71: Tier 4-6 | C71: First look: the medieval world | I71: 16 | Q71: =SUM(D71:P71) -> 16 | R71: =IF(Q71=Topics!M71,"ok","differs from Topics") -> ok
A72: T4-6-040 | B72: Tier 4-6 | C72: First look: the early modern world | I72: 14 | Q72: =SUM(D72:P72) -> 14 | R72: =IF(Q72=Topics!M72,"ok","differs from Topics") -> ok
A73: T4-6-041 | B73: Tier 4-6 | C73: First look: revolutions, industry and empire | I73: 13 | Q73: =SUM(D73:P73) -> 13 | R73: =IF(Q73=Topics!M73,"ok","differs from Topics") -> ok
A74: T4-6-042 | B74: Tier 4-6 | C74: First look: the twentieth century | I74: 16 | Q74: =SUM(D74:P74) -> 16 | R74: =IF(Q74=Topics!M74,"ok","differs from Topics") -> ok
A75: T4-6-043 | B75: Tier 4-6 | C75: First look: Africa from Lalibela to independence | I75: 9 | Q75: =SUM(D75:P75) -> 9 | R75: =IF(Q75=Topics!M75,"ok","differs from Topics") -> ok
A76: T4-6-044 | B76: Tier 4-6 | C76: First look: Asia | I76: 8 | Q76: =SUM(D76:P76) -> 8 | R76: =IF(Q76=Topics!M76,"ok","differs from Topics") -> ok
A77: T4-6-045 | B77: Tier 4-6 | C77: First look: Latin America and the Middle East | I77: 5 | Q77: =SUM(D77:P77) -> 5 | R77: =IF(Q77=Topics!M77,"ok","differs from Topics") -> ok
A78: T4-6-046 | B78: Tier 4-6 | C78: African and local religions as history | H78: 3 | I78: 3 | Q78: =SUM(D78:P78) -> 6 | R78: =IF(Q78=Topics!M78,"ok","differs from Topics") -> ok
A79: T7-9-001 | B79: Tier 7-9 | C79: Byzantium and Kievan Rus | J79: 3 | L79: 1 | Q79: =SUM(D79:P79) -> 4 | R79: =IF(Q79=Topics!M79,"ok","differs from Topics") -> ok
A80: T7-9-002 | B80: Tier 7-9 | C80: Muhammad, the caliphates and the spread of Islam | J80: 8 | L80: 1 | Q80: =SUM(D80:P80) -> 9 | R80: =IF(Q80=Topics!M80,"ok","differs from Topics") -> ok
A81: T7-9-003 | B81: Tier 7-9 | C81: Baghdad, Cordoba and Islamic scholars | J81: 6 | L81: 3 | Q81: =SUM(D81:P81) -> 9 | R81: =IF(Q81=Topics!M81,"ok","differs from Topics") -> ok
A82: T7-9-004 | B82: Tier 7-9 | C82: The Vikings | L82: 1 | Q82: =SUM(D82:P82) -> 1 | R82: =IF(Q82=Topics!M82,"ok","differs from Topics") -> ok
A83: T7-9-005 | B83: Tier 7-9 | C83: Medieval Europe: lords, peasants, nuns, monks and towns | J83: 8 | L83: 1 | Q83: =SUM(D83:P83) -> 9 | R83: =IF(Q83=Topics!M83,"ok","differs from Topics") -> ok
A84: T7-9-006 | B84: Tier 7-9 | C84: The Crusades and Saladin | J84: 4 | L84: 1 | Q84: =SUM(D84:P84) -> 5 | R84: =IF(Q84=Topics!M84,"ok","differs from Topics") -> ok
A85: T7-9-007 | B85: Tier 7-9 | C85: Tang and Song China | J85: 9 | Q85: =SUM(D85:P85) -> 9 | R85: =IF(Q85=Topics!M85,"ok","differs from Topics") -> ok
A86: T7-9-008 | B86: Tier 7-9 | C86: Korea and Japan before 1600 | J86: 8 | Q86: =SUM(D86:P86) -> 8 | R86: =IF(Q86=Topics!M86,"ok","differs from Topics") -> ok
A87: T7-9-009 | B87: Tier 7-9 | C87: The Silk Road in its great age | L87: 1 | Q87: =SUM(D87:P87) -> 1 | R87: =IF(Q87=Topics!M87,"ok","differs from Topics") -> ok
A88: T7-9-010 | B88: Tier 7-9 | C88: Genghis Khan and the Mongol empires | J88: 6 | L88: 1 | Q88: =SUM(D88:P88) -> 7 | R88: =IF(Q88=Topics!M88,"ok","differs from Topics") -> ok
A89: T7-9-011 | B89: Tier 7-9 | C89: The Black Death and the 1300s | J89: 3 | L89: 1 | Q89: =SUM(D89:P89) -> 4 | R89: =IF(Q89=Topics!M89,"ok","differs from Topics") -> ok
A90: T7-9-012 | B90: Tier 7-9 | C90: Mali and the empires of West Africa | J90: 8 | L90: 1 | Q90: =SUM(D90:P90) -> 9 | R90: =IF(Q90=Topics!M90,"ok","differs from Topics") -> ok
A91: T7-9-013 | B91: Tier 7-9 | C91: The Swahili coast and the Indian Ocean | J91: 6 | L91: 1 | Q91: =SUM(D91:P91) -> 7 | R91: =IF(Q91=Topics!M91,"ok","differs from Topics") -> ok
A92: T7-9-014 | B92: Tier 7-9 | C92: Great Zimbabwe and southern Africa | J92: 6 | Q92: =SUM(D92:P92) -> 6 | R92: =IF(Q92=Topics!M92,"ok","differs from Topics") -> ok
A93: T7-9-015 | B93: Tier 7-9 | C93: Ethiopia and Lalibela | J93: 5 | Q93: =SUM(D93:P93) -> 5 | R93: =IF(Q93=Topics!M93,"ok","differs from Topics") -> ok
A94: T7-9-016 | B94: Tier 7-9 | C94: Ife, Benin and the forest kingdoms | J94: 4 | K94: 2 | Q94: =SUM(D94:P94) -> 6 | R94: =IF(Q94=Topics!M94,"ok","differs from Topics") -> ok
A95: T7-9-017 | B95: Tier 7-9 | C95: Ibn Battuta | L95: 1 | Q95: =SUM(D95:P95) -> 1 | R95: =IF(Q95=Topics!M95,"ok","differs from Topics") -> ok
A96: T7-9-018 | B96: Tier 7-9 | C96: The Delhi Sultanate and Vijayanagara | J96: 5 | Q96: =SUM(D96:P96) -> 5 | R96: =IF(Q96=Topics!M96,"ok","differs from Topics") -> ok
A97: T7-9-019 | B97: Tier 7-9 | C97: Southeast Asia: Srivijaya to Dai Viet | J97: 8 | Q97: =SUM(D97:P97) -> 8 | R97: =IF(Q97=Topics!M97,"ok","differs from Topics") -> ok
A98: T7-9-020 | B98: Tier 7-9 | C98: Polynesian navigators | J98: 5 | Q98: =SUM(D98:P98) -> 5 | R98: =IF(Q98=Topics!M98,"ok","differs from Topics") -> ok
A99: T7-9-021 | B99: Tier 7-9 | C99: The Maya after the classic age | J99: 2 | L99: 1 | Q99: =SUM(D99:P99) -> 3 | R99: =IF(Q99=Topics!M99,"ok","differs from Topics") -> ok
A100: T7-9-022 | B100: Tier 7-9 | C100: Cahokia and North America | J100: 3 | Q100: =SUM(D100:P100) -> 3 | R100: =IF(Q100=Topics!M100,"ok","differs from Topics") -> ok
...

Sheet Tiers
A1: Tier | B1: Levels | C1: What the tier covers | D1: What a card looks like | E1: Cards
A2: Tier 1-3 | B2: 1, 2, 3 | C2: Level 1 is the child's world then and now, with time, family, homes, travel, festivals and leaders. Level 2 covers human ancestors in East Africa, Stone Age life, and family life then and now in two places. Level 3 covers first farmers, towns and cities, writing, money, famous places, journeys and helpers from every continent. All new. | D2: Level 1 about 15 to 25 words in 3 to 6 sentences, no glossary, one-word options, written to be read aloud by a teacher or parent. Level 2 about 40 words in 3 to 6 sentences, at most one glossary word. Level 3 about 60 to 70 words in 5 to 9 sentences on the front, as on the sample card about paper, with up to three glossary words on the back. The picture shows the setting or one clue, never the answer, and no question asks what the picture shows. One concrete thing per card. Questions: which one, what was it for, which came first, then or now. Nothing frightening. | E2: =SUMIF(Topics!$B$2:$B$213,A2,Topics!$M$2:$M$213) -> 223
A3: Tier 4-6 | B3: 4, 5, 6 | C3: Levels 4-5: human origins to about 500 CE, Big Eras 1-4, with farming, river civilisations, early states in Africa, Asia and the Americas, traditional leadership, early belief and classical empires. Level 6: the 80 existing level-6 cards plus first-look cards on Africa, Asia, Latin America and the Middle East, so every pupil meets the whole timeline once. | D3: House format, about 80 to 110 words in 7 to 12 sentences of about seven words, glossary for words outside the 1,000 most common. Anonymised clue chain. Questions: identify, order two events, one simple cause or result. Centuries, not exact years. Belief marked as belief. | E3: =SUMIF(Topics!$B$2:$B$213,A3,Topics!$M$2:$M$213) -> 320
A4: Tier 7-9 | B4: 7, 8, 9 | C4: About 300 to 1900, Big Eras 5-7. Level 7: Islam and the medieval worlds of Africa, Asia, Europe, the Americas and the Pacific, and how we know about states with few written records. Level 8: 1450-1800, with voyages, the Columbian Exchange, slave trades, land empires, and limited and absolute monarchy. Level 9: 1750-1900, with revolutions, industry, abolition, migration and conquest, plus the 80 existing level-9 cards. | D4: About 100 to 130 words in 9 to 12 sentences, three to five glossary words, two or three linked clues across regions or from cause to effect. Questions on cause and consequence, comparison, change over time and how we know. Key dates allowed. Conquest and slavery told from more than one side, no gore. | E4: =SUMIF(Topics!$B$2:$B$213,A4,Topics!$M$2:$M$213) -> 405
A5: Tier 10-U | B5: 10, 11, 12, U | C5: Level 10: 1848-1945 on Cambridge IGCSE Option A, Option B key questions 1-3 and depth studies A-E. Level 11: the world since 1945, with IGCSE Option B key questions 4-6 for the Cold War and the other layers for decolonisation, rights, globalisation and the environment. Level 12: Cambridge AS Level depth and comparison across eras, with 160 existing cards. U: A Level Papers 3 and 4, AP World History: Modern and the NCHS grade 9-12 standards, for evidence, myths and interpretations, with 80 existing cards. | D5: About 110 to 140 words in 9 to 12 short sentences, with abstract terms such as mandate or interpretation in the glossary. Levels 10-11 ask for causes, results and significance; 12 compares and tracks change; U asks which evidence supports a claim or which view a historian holds. One defensible answer of four. Sensitive topics through facts and testimony, with no victim images. | E5: =SUMIF(Topics!$B$2:$B$213,A5,Topics!$M$2:$M$213) -> 571

Sheet Level outcomes
A1: Level | B1: Tier | C1: Outcome ID | D1: By the end of the level, students can | E1: Standard mapping | F1: Topic rows that teach it
A2: 1 | B2: Tier 1-3 | C2: H1.1 | D2: By the end of level 1, students can use time words such as before, after, long ago and today, and put two events in order. | E2: NCHS K-4 Historical Thinking Standard 1, Chronological Thinking; BNCC EF02HI06; Cambridge Primary Humanities 0065, Past strand | F2: T1-3-001
A3: 1 | B3: Tier 1-3 | C3: H1.2 | D3: By the end of level 1, students can tell an old object from a new one and say what each was for, such as an oil lamp and a light bulb. | E3: NCHS K-4 Topic 4, Standard 8A; England National Curriculum 2013, KS1, changes within living memory | F3: T1-3-003, T1-3-030
A4: 1 | B4: Tier 1-3 | C4: H1.3 | D4: By the end of level 1, students can describe how children lived long ago, such as how they learned, played and travelled, and say what has changed and what is still the same today. | E4: NCHS K-4 Topic 1, Standard 1; Tanzania HTM primary 2023, Std III; IB PYP Social studies scope and sequence 2008, age band 5-7, reference only | F4: T1-3-002, T1-3-003, T1-3-030
A5: 1 | B5: Tier 1-3 | C5: H1.4 | D5: By the end of level 1, students can name clues about the past, such as old objects, photographs, buildings and stories told by grandparents. | E5: Cambridge Primary Humanities 0065, Past strand, how we construct the past; NCHS K-4 Topic 4, Standard 7A | F5: T1-3-004
A6: 1 | B6: Tier 1-3 | C6: H1.5 | D6: By the end of level 1, students can recognise that people everywhere mark special days with stories, songs and festivals, and that some festivals come from religious belief. | E6: NCHS K-4 Topic 4, Standard 7A, folktales, holidays and ceremonies; Tanzania HTM primary 2023, Std III | F6: T1-3-005, T1-3-024
A7: 1 | B7: Tier 1-3 | C7: H1.6 | D7: By the end of level 1, students can compare how people travelled and sent messages long ago and today, such as camels, boats, drums, letters and phones. | E7: NCHS K-4 Topic 4, Standards 8B and 8C | F7: T1-3-006
A8: 1 | B8: Tier 1-3 | C8: H1.7 | D8: By the end of level 1, students can name who makes rules in a family, a school and a village, and say that leaders long ago were often elders, chiefs, kings or queens. | E8: WHFUA key theme Uses and Abuses of Power; Tanzania HTM primary 2023, Std III, leadership at family, clan and school level; Bhutan Social Studies 2025, Class IV, local government | F8: T1-3-007
A9: 2 | B9: Tier 1-3 | C9: H2.1 | D9: By the end of level 2, students can say that the first humans and their older ancestors lived in Africa, and that very old footprints and bones of these ancestors were found in Tanzania and Ethiopia. | E9: WHFUA Big Era 1, Landscape 1.2; NCHS World History Era 1, Standard 1; Kenya KICD Junior School Grade 8 | F9: T1-3-008
A10: 2 | B10: Tier 1-3 | C10: H2.2 | D10: By the end of level 2, students can describe how early people found food by hunting, fishing and gathering plants. | E10: NCHS K-4 Topic 4, Standard 8A; WHFUA Big Era 2, Landscape 2.1 | F10: T1-3-010
A11: 2 | B11: Tier 1-3 | C11: H2.3 | D11: By the end of level 2, students can name the first tools and skills of early people: stone tools, fire, clothes and shelters. | E11: NCHS K-4 Topic 4, Standard 8A; England National Curriculum 2013, KS2, Stone Age to Iron Age | F11: T1-3-009
A12: 2 | B12: Tier 1-3 | C12: H2.4 | D12: By the end of level 2, students can recognise that early people painted on rocks and made beads, and that these are clues about their lives. | E12: WHFUA Big Era 2, Landscape 2.1; NCHS K-4 Topic 4, Standard 7A | F12: T1-3-011
... A104: U | B104: Tier 10-U | C104: HU.8 | D104: By the end of university level, students can explain when, by whom and why the sources about a religious founder were written, and what historians can and cannot know from them. | E104: AP World History: Modern Skill 2, Sourcing and Situation; Cambridge 9489 AO3; Tanzania History A-level 2023, Form V | F104: T10-U-004

Sheet Standards
A1: Role | B1: Standard | C1: Code and version | D1: Levels | E1: Used for | F1: Link
A2: Primary: content spine | B2: World History for Us All, Big Eras 1-9 (UCLA Public History Initiative) | C2: Big Eras 1-9 | D2: 1-U | E2: Global, chronological spine for every level, including everything before 1774 that Cambridge does not examine. | F2: https://whfua.history.ucla.edu/bigeras.php
A3: Primary: outcome wording | B3: National Standards for History, Basic Edition (NCHS, UCLA) | C3: 1996; K-4 standards and World History Eras 1-9 for grades 5-12 | D3: 1-12 | E3: Outcome wording with grade bands: K-4 standards for levels 1-4 and world-history Eras 1-9 for grades 5-12; Historical Thinking Standards for skills. | F3: https://phi.history.ucla.edu/nchs/world-history-content-standards/
A4: Primary: exam standard | B4: Cambridge IGCSE History (same content: IGCSE 9-1 History 0977, O Level History 2147) | C4: 0470, syllabus 2027-2028 and 2029-2030 | D4: 10-11 | E4: Named exam standard for levels 10-11: content from 1848 to about 1989, Option A nineteenth century, Option B international relations since 1919, depth studies A-E. Assessment objectives AO1 and AO2. | F4: https://www.cambridgeinternational.org/programmes-and-qualifications/cambridge-igcse-history-0470/
A5: Primary: exam standard | B5: Cambridge International AS & A Level History | C5: 9489, syllabus 2027-2029, version 2 | D5: 12-U | E5: Named exam standard for level 12, with Papers 3 and 4 at U: content and key concepts from 1774 to 1994. | F5: https://www.cambridgeinternational.org/programmes-and-qualifications/cambridge-international-as-and-a-level-history-9489/
A6: Primary: university benchmark | B6: AP World History: Modern (College Board) | C6: Course and Exam Description, effective fall 2026 | D6: U | E6: University-equivalent survey of world history from about 1200 to the present; the College Board designs it as the equivalent of an introductory college course. | F6: https://apcentral.collegeboard.org/courses/ap-world-history
A7: Supporting | B7: Cambridge Primary Humanities, Past strand | C7: 0065, Stages 1-6 | D7: 1-6 | E7: Supporting wording for the history skills outcomes for levels 1-6: time and chronology, change, how we know about the past. Cambridge prescribes no history content at this stage. | F7: https://www.cambridgeinternational.org/programmes-and-qualifications/cambridge-primary/curriculum/humanities/
A8: Supporting | B8: Cambridge Lower Secondary Humanities, Past strand | C8: 0839, Stages 7-9 | D8: 7-9 | E8: Supporting wording for the history skills outcomes for levels 7-9. No prescribed content. | F8: https://www.cambridgeinternational.org/programmes-and-qualifications/cambridge-lower-secondary/curriculum/humanities/
A9: Reference | B9: IB Diploma Programme History | C9: Guide for first assessment 2028 | D9: 11-12 | E9: Cross-check of regional balance at upper secondary. Cited as a reference only; the cards are not endorsed by the IB. | F9: https://ibo.org/programmes/diploma-programme/curriculum/individuals-and-societies/history/
A10: Relevance check | B10: Bhutan History Curriculum Framework, Classes VII-XII | C10: Department of School Education, 2022 | D10: 7-12 | E10: World History strand and topic weights for Bhutanese pupils; Bhutan has aligned its curriculum with Cambridge since 2025. | F10: https://rec.gov.bt/download/56/curriculum-frameworks/5365/history-curriculum-framework-2022.pdf
A11: Relevance check | B11: Tanzania History syllabi, Form I-IV and Form V-VI | C11: Tanzania Institute of Education, 2023 | D11: 7-12 | E11: Africa-centred topics and competences for Tanzanian pupils. | F11: https://www.tie.go.tz/publications/syllabus-for-lower-secondary-academics
A12: Relevance check | B12: India NCERT, Kenya CBC, Brazil BNCC, England National Curriculum | C12: Current editions, checked October 2026 | D12: 1-12 | E12: Common core of world-history topics across national curricula in the regions the cards serve. | F12: https://www.gov.uk/government/publications/national-curriculum-in-england-history-programmes-of-study/national-curriculum-in-england-history-programmes-of-study
... A15: Not used | B15: ICCS (IEA) | C15: - | D15: - | E15: Assesses civic and citizenship knowledge at grade 8, not history. | F15: https://www.iea.nl/studies/iea/iccs

Sheet Existing cards
A1: Card ID | B1: Topic | C1: Card | D1: Level | E1: Tier | F1: Title | G1: Question | H1: Answer | I1: Map row | J1: Card set
A2: 001-1 | B2: Ancient Egypt: the pyramids | C2: 1 | D2: H 6 | E2: Tier 4-6 | F2: A land by one long river | G2: Which land is this? | H2: Egypt | I2: T4-6-009 | J2: ancient-egypt-pyramids
A3: 001-2 | B3: Ancient Egypt: the pyramids | C3: 2 | D3: H 9 | E3: Tier 7-9 | F3: Thousands of workers, no modern machines | G3: Which land is this? | H3: Egypt | I3: T7-9-066 | J3: ancient-egypt-pyramids
A4: 001-3 | B4: Ancient Egypt: the pyramids | C4: 3 | D4: H 12 | E4: Tier 10-U | F4: A mountain of stone | G4: Which land is this? | H4: Egypt | I4: T10-U-001 | J4: ancient-egypt-pyramids
A5: 001-4 | B5: Ancient Egypt: the pyramids | C5: 4 | D5: H 12 | E5: Tier 10-U | F5: The scribes and the flood | G5: Which land is this? | H5: Egypt | I5: T10-U-001 | J5: ancient-egypt-pyramids
A6: 001-5 | B6: Ancient Egypt: the pyramids | C6: 5 | D6: H U | E6: Tier 10-U | F6: The stone with three scripts | G6: Which land is this? | H6: Egypt | I6: T10-U-001 | J6: ancient-egypt-pyramids
A7: 002-1 | B7: Mesopotamia: the first cities and writing | C7: 1 | D7: H 6 | E7: Tier 4-6 | F7: The Land Between Two Rivers | G7: Which land is this? | H7: Mesopotamia | I7: T4-6-010 | J7: mesopotamia
A8: 002-2 | B8: Mesopotamia: the first cities and writing | C8: 2 | D8: H 9 | E8: Tier 7-9 | F8: Why People Invent Writing | G8: Which land is this? | H8: Mesopotamia | I8: T7-9-066 | J8: mesopotamia
A9: 002-3 | B9: Mesopotamia: the first cities and writing | C9: 3 | D9: H 12 | E9: Tier 10-U | F9: The City: A Big Invention | G9: Which land is this? | H9: Mesopotamia | I9: T10-U-001 | J9: mesopotamia
A10: 002-4 | B10: Mesopotamia: the first cities and writing | C10: 4 | D10: H 12 | E10: Tier 10-U | F10: The First Great Story | G10: Which land is this? | H10: Mesopotamia | I10: T10-U-001 | J10: mesopotamia
A11: 002-5 | B11: Mesopotamia: the first cities and writing | C11: 5 | D11: H U | E11: Tier 10-U | F11: Clay Outlasts Paper | G11: Which land is this? | H11: Mesopotamia | I11: T10-U-001 | J11: mesopotamia
A12: 003-1 | B12: Hammurabi and his law code | C12: 1 | D12: H 6 | E12: Tier 4-6 | F12: The King and the Tall Law Stone | G12: Who is King X? | H12: Hammurabi | I12: T4-6-010 | J12: hammurabi
A13: 003-2 | B13: Hammurabi and his law code | C13: 2 | D13: H 9 | E13: Tier 7-9 | F13: Laws for All to See | G13: Who is King X? | H13: Hammurabi | I13: T7-9-066 | J13: hammurabi
... A401: 080-5 | B401: The Ottoman Empire | C401: 5 | D401: H U | E401: Tier 10-U | F401: Decline, or something else? | G401: Which empire is Empire X? | H401: The Ottoman Empire | I401: T10-U-017 | J401: ottoman-empire
